{
"meta":{"test_sets":[],"test_metrics":[],"learn_metrics":[{"best_value":"Min","name":"RMSE"}],"launch_mode":"Train","parameters":"","iteration_count":1000,"learn_sets":["learn"],"name":"experiment"},
"iterations":[
{"learn":[14.59871775],"iteration":0,"passed_time":0.1565795131,"remaining_time":156.4229336},
{"learn":[14.22518863],"iteration":1,"passed_time":0.1573366849,"remaining_time":78.51100579},
{"learn":[13.8866124],"iteration":2,"passed_time":0.1580152033,"remaining_time":52.51371925},
{"learn":[13.52356875],"iteration":3,"passed_time":0.1586662345,"remaining_time":39.50789239},
{"learn":[13.18870211],"iteration":4,"passed_time":0.1592081221,"remaining_time":31.68241631},
{"learn":[12.9124226],"iteration":5,"passed_time":0.1598627956,"remaining_time":26.48393648},
{"learn":[12.60003351],"iteration":6,"passed_time":0.1605892476,"remaining_time":22.78073184},
{"learn":[12.32990573],"iteration":7,"passed_time":0.1616620911,"remaining_time":20.0460993},
{"learn":[12.0660619],"iteration":8,"passed_time":0.1623017158,"remaining_time":17.87122226},
{"learn":[11.77309809],"iteration":9,"passed_time":0.1629457514,"remaining_time":16.13162939},
{"learn":[11.49227636],"iteration":10,"passed_time":0.1635972961,"remaining_time":14.70888417},
{"learn":[11.26264833],"iteration":11,"passed_time":0.1643471275,"remaining_time":13.53124683},
{"learn":[11.04260393],"iteration":12,"passed_time":0.1649231216,"remaining_time":12.52147084},
{"learn":[10.79916926],"iteration":13,"passed_time":0.1654783361,"remaining_time":11.65440281},
{"learn":[10.5541002],"iteration":14,"passed_time":0.1660947389,"remaining_time":10.90688785},
{"learn":[10.31918115],"iteration":15,"passed_time":0.1667250206,"remaining_time":10.25358877},
{"learn":[10.10004441],"iteration":16,"passed_time":0.1672854911,"remaining_time":9.673037516},
{"learn":[9.894556723],"iteration":17,"passed_time":0.1677864343,"remaining_time":9.153682141},
{"learn":[9.690174082],"iteration":18,"passed_time":0.168346949,"remaining_time":8.692018787},
{"learn":[9.506034866],"iteration":19,"passed_time":0.1688289621,"remaining_time":8.272619145},
{"learn":[9.338524633],"iteration":20,"passed_time":0.1693387139,"remaining_time":7.894409568},
{"learn":[9.170203312],"iteration":21,"passed_time":0.169967159,"remaining_time":7.555812797},
{"learn":[9.010299969],"iteration":22,"passed_time":0.1705724901,"remaining_time":7.245622733},
{"learn":[8.843866678],"iteration":23,"passed_time":0.1712442583,"remaining_time":6.96393317},
{"learn":[8.690548059],"iteration":24,"passed_time":0.1719398405,"remaining_time":6.70565378},
{"learn":[8.555307687],"iteration":25,"passed_time":0.1725399304,"remaining_time":6.463611239},
{"learn":[8.413851302],"iteration":26,"passed_time":0.1731376437,"remaining_time":6.239367678},
{"learn":[8.29256019],"iteration":27,"passed_time":0.1737896663,"remaining_time":6.03298413},
{"learn":[8.162193833],"iteration":28,"passed_time":0.1745608778,"remaining_time":5.844779737},
{"learn":[8.040736294],"iteration":29,"passed_time":0.1755031039,"remaining_time":5.674600359},
{"learn":[7.921220278],"iteration":30,"passed_time":0.1762967234,"remaining_time":5.510694355},
{"learn":[7.809589039],"iteration":31,"passed_time":0.1770180942,"remaining_time":5.35479735},
{"learn":[7.699675801],"iteration":32,"passed_time":0.1777932078,"remaining_time":5.209879757},
{"learn":[7.60645267],"iteration":33,"passed_time":0.1786917505,"remaining_time":5.076947969},
{"learn":[7.498880302],"iteration":34,"passed_time":0.1794087729,"remaining_time":4.946556167},
{"learn":[7.401158744],"iteration":35,"passed_time":0.1801335186,"remaining_time":4.823575331},
{"learn":[7.306431077],"iteration":36,"passed_time":0.180876368,"remaining_time":4.70767412},
{"learn":[7.223863468],"iteration":37,"passed_time":0.1816307924,"remaining_time":4.598126902},
{"learn":[7.143477682],"iteration":38,"passed_time":0.1822544241,"remaining_time":4.490935937},
{"learn":[7.062817131],"iteration":39,"passed_time":0.1828700098,"remaining_time":4.388880236},
{"learn":[6.990793435],"iteration":40,"passed_time":0.1834949333,"remaining_time":4.291991245},
{"learn":[6.931862224],"iteration":41,"passed_time":0.1841467591,"remaining_time":4.200299886},
{"learn":[6.858296558],"iteration":42,"passed_time":0.1848200499,"remaining_time":4.113320646},
{"learn":[6.786268161],"iteration":43,"passed_time":0.1853853876,"remaining_time":4.027918876},
{"learn":[6.717118549],"iteration":44,"passed_time":0.185983944,"remaining_time":3.946992589},
{"learn":[6.652948106],"iteration":45,"passed_time":0.1865192361,"remaining_time":3.868246767},
{"learn":[6.589686076],"iteration":46,"passed_time":0.1870809303,"remaining_time":3.793364395},
{"learn":[6.531283097],"iteration":47,"passed_time":0.1876894583,"remaining_time":3.722507589},
{"learn":[6.471368031],"iteration":48,"passed_time":0.1887817843,"remaining_time":3.663907691},
{"learn":[6.416481395],"iteration":49,"passed_time":0.1894530192,"remaining_time":3.599607366},
{"learn":[6.369870822],"iteration":50,"passed_time":0.1900833547,"remaining_time":3.537041247},
{"learn":[6.325678067],"iteration":51,"passed_time":0.1906487597,"remaining_time":3.475673542},
{"learn":[6.275766122],"iteration":52,"passed_time":0.191143168,"remaining_time":3.4153317},
{"learn":[6.224773967],"iteration":53,"passed_time":0.1917318286,"remaining_time":3.358857589},
{"learn":[6.182249254],"iteration":54,"passed_time":0.1922638068,"remaining_time":3.303441771},
{"learn":[6.139904173],"iteration":55,"passed_time":0.1928667909,"remaining_time":3.251183046},
{"learn":[6.100525536],"iteration":56,"passed_time":0.1934290515,"remaining_time":3.20006308},
{"learn":[6.062568564],"iteration":57,"passed_time":0.1939946365,"remaining_time":3.150740476},
{"learn":[6.030559288],"iteration":58,"passed_time":0.1946003958,"remaining_time":3.103711397},
{"learn":[5.997931376],"iteration":59,"passed_time":0.1951481168,"remaining_time":3.057320496},
{"learn":[5.964103835],"iteration":60,"passed_time":0.1956886421,"remaining_time":3.012321884},
{"learn":[5.933729724],"iteration":61,"passed_time":0.1962797286,"remaining_time":2.969522346},
{"learn":[5.901932711],"iteration":62,"passed_time":0.1968740986,"remaining_time":2.928111594},
{"learn":[5.873727795],"iteration":63,"passed_time":0.1974557436,"remaining_time":2.88779025},
{"learn":[5.846485734],"iteration":64,"passed_time":0.1980890835,"remaining_time":2.849435278},
{"learn":[5.820630862],"iteration":65,"passed_time":0.1987204429,"remaining_time":2.812195358},
{"learn":[5.793646238],"iteration":66,"passed_time":0.1993643558,"remaining_time":2.776223044},
{"learn":[5.765388646],"iteration":67,"passed_time":0.1999592871,"remaining_time":2.740618464},
{"learn":[5.747073912],"iteration":68,"passed_time":0.2005399822,"remaining_time":2.705836572},
{"learn":[5.722315217],"iteration":69,"passed_time":0.201088228,"remaining_time":2.671600743},
{"learn":[5.699970599],"iteration":70,"passed_time":0.2016824717,"remaining_time":2.638915722},
{"learn":[5.682732647],"iteration":71,"passed_time":0.2024998103,"remaining_time":2.609997555},
{"learn":[5.663525791],"iteration":72,"passed_time":0.2034972037,"remaining_time":2.584135724},
{"learn":[5.642381613],"iteration":73,"passed_time":0.2045211414,"remaining_time":2.559278067},
{"learn":[5.621404779],"iteration":74,"passed_time":0.2055382503,"remaining_time":2.534971753},
{"learn":[5.602460129],"iteration":75,"passed_time":0.2061952407,"remaining_time":2.506900031},
{"learn":[5.587337574],"iteration":76,"passed_time":0.2069194335,"remaining_time":2.480345936},
{"learn":[5.572393026],"iteration":77,"passed_time":0.2076537571,"remaining_time":2.454573897},
{"learn":[5.558425806],"iteration":78,"passed_time":0.208285466,"remaining_time":2.428239421},
{"learn":[5.541518902],"iteration":79,"passed_time":0.2090521624,"remaining_time":2.404099868},
{"learn":[5.526157283],"iteration":80,"passed_time":0.2096899205,"remaining_time":2.37907453},
{"learn":[5.511746977],"iteration":81,"passed_time":0.2103370868,"remaining_time":2.354749337},
{"learn":[5.504975022],"iteration":82,"passed_time":0.2107371502,"remaining_time":2.328264659},
{"learn":[5.493980522],"iteration":83,"passed_time":0.2115666281,"remaining_time":2.307083707},
{"learn":[5.480745463],"iteration":84,"passed_time":0.2123433683,"remaining_time":2.285813905},
{"learn":[5.464052013],"iteration":85,"passed_time":0.213144173,"remaining_time":2.265276444},
{"learn":[5.449143727],"iteration":86,"passed_time":0.2138450718,"remaining_time":2.244144259},
{"learn":[5.438255432],"iteration":87,"passed_time":0.2145265261,"remaining_time":2.223274907},
{"learn":[5.425927931],"iteration":88,"passed_time":0.2152546295,"remaining_time":2.203336713},
{"learn":[5.412331217],"iteration":89,"passed_time":0.2158700256,"remaining_time":2.182685814},
{"learn":[5.400691499],"iteration":90,"passed_time":0.2166839848,"remaining_time":2.164458705},
{"learn":[5.391618744],"iteration":91,"passed_time":0.2175949053,"remaining_time":2.147567109},
{"learn":[5.380766572],"iteration":92,"passed_time":0.2183530554,"remaining_time":2.12952926},
{"learn":[5.372207183],"iteration":93,"passed_time":0.2192978706,"remaining_time":2.113658199},
{"learn":[5.362918837],"iteration":94,"passed_time":0.2200977448,"remaining_time":2.096720622},
{"learn":[5.348292324],"iteration":95,"passed_time":0.220946577,"remaining_time":2.080580267},
{"learn":[5.339772295],"iteration":96,"passed_time":0.221821961,"remaining_time":2.06500238},
{"learn":[5.331515983],"iteration":97,"passed_time":0.2225510146,"remaining_time":2.048377706},
{"learn":[5.323861644],"iteration":98,"passed_time":0.2232763997,"remaining_time":2.032040769},
{"learn":[5.313277281],"iteration":99,"passed_time":0.2240705593,"remaining_time":2.016635034},
{"learn":[5.30685627],"iteration":100,"passed_time":0.2247765986,"remaining_time":2.000734279},
{"learn":[5.29652059],"iteration":101,"passed_time":0.2254831607,"remaining_time":1.985136062},
{"learn":[5.288350766],"iteration":102,"passed_time":0.2262720747,"remaining_time":1.970544185},
{"learn":[5.27993346],"iteration":103,"passed_time":0.2270996467,"remaining_time":1.956550802},
{"learn":[5.271789139],"iteration":104,"passed_time":0.2277960969,"remaining_time":1.94169054},
{"learn":[5.262684686],"iteration":105,"passed_time":0.2286577965,"remaining_time":1.928491227},
{"learn":[5.251619772],"iteration":106,"passed_time":0.2293145435,"remaining_time":1.913812031},
{"learn":[5.241012171],"iteration":107,"passed_time":0.230172895,"remaining_time":1.901057614},
{"learn":[5.232684032],"iteration":108,"passed_time":0.2309564973,"remaining_time":1.88791045},
{"learn":[5.224267141],"iteration":109,"passed_time":0.2318219779,"remaining_time":1.875650548},
{"learn":[5.216324968],"iteration":110,"passed_time":0.2328498494,"remaining_time":1.864896541},
{"learn":[5.211102527],"iteration":111,"passed_time":0.2335287992,"remaining_time":1.851549765},
{"learn":[5.206364257],"iteration":112,"passed_time":0.2341567239,"remaining_time":1.838026673},
{"learn":[5.196937641],"iteration":113,"passed_time":0.2348275122,"remaining_time":1.825062946},
{"learn":[5.190746047],"iteration":114,"passed_time":0.2355709226,"remaining_time":1.812871882},
{"learn":[5.181885213],"iteration":115,"passed_time":0.2362443265,"remaining_time":1.800344695},
{"learn":[5.178293568],"iteration":116,"passed_time":0.2368239424,"remaining_time":1.787312317},
{"learn":[5.170991438],"iteration":117,"passed_time":0.2374754823,"remaining_time":1.775028605},
{"learn":[5.166257212],"iteration":118,"passed_time":0.2381632322,"remaining_time":1.763208467},
{"learn":[5.161421246],"iteration":119,"passed_time":0.2387908655,"remaining_time":1.751133014},
{"learn":[5.158223542],"iteration":120,"passed_time":0.2394550395,"remaining_time":1.739512229},
{"learn":[5.15470988],"iteration":121,"passed_time":0.2399488733,"remaining_time":1.72684517},
{"learn":[5.146388143],"iteration":122,"passed_time":0.2406177893,"remaining_time":1.7156244},
{"learn":[5.139529364],"iteration":123,"passed_time":0.2411291809,"remaining_time":1.703460987},
{"learn":[5.134276023],"iteration":124,"passed_time":0.2417315423,"remaining_time":1.692120796},
{"learn":[5.128536065],"iteration":125,"passed_time":0.2424689253,"remaining_time":1.681887625},
{"learn":[5.123300353],"iteration":126,"passed_time":0.2430282993,"remaining_time":1.670580357},
{"learn":[5.116200518],"iteration":127,"passed_time":0.2435802003,"remaining_time":1.659390114},
{"learn":[5.108728704],"iteration":128,"passed_time":0.244124657,"remaining_time":1.648314545},
{"learn":[5.104075866],"iteration":129,"passed_time":0.244635126,"remaining_time":1.637173536},
{"learn":[5.100317606],"iteration":130,"passed_time":0.2451358523,"remaining_time":1.626130196},
{"learn":[5.095814182],"iteration":131,"passed_time":0.2457579854,"remaining_time":1.616044935},
{"learn":[5.092146915],"iteration":132,"passed_time":0.2465290302,"remaining_time":1.6070727},
{"learn":[5.085258329],"iteration":133,"passed_time":0.2473520193,"remaining_time":1.598558572},
{"learn":[5.079219421],"iteration":134,"passed_time":0.2481866638,"remaining_time":1.590233068},
{"learn":[5.076476829],"iteration":135,"passed_time":0.2489987155,"remaining_time":1.581874192},
{"learn":[5.072133867],"iteration":136,"passed_time":0.2496566015,"remaining_time":1.572654358},
{"learn":[5.067031564],"iteration":137,"passed_time":0.2502872669,"remaining_time":1.56338858},
{"learn":[5.061358312],"iteration":138,"passed_time":0.2508229965,"remaining_time":1.553658993},
{"learn":[5.056759124],"iteration":139,"passed_time":0.2513683969,"remaining_time":1.544120153},
{"learn":[5.050254],"iteration":140,"passed_time":0.2518566985,"remaining_time":1.534361021},
{"learn":[5.048376474],"iteration":141,"passed_time":0.2522355177,"remaining_time":1.524070945},
{"learn":[5.042603751],"iteration":142,"passed_time":0.2528489666,"remaining_time":1.515325625},
{"learn":[5.037477349],"iteration":143,"passed_time":0.2534375117,"remaining_time":1.506545208},
{"learn":[5.03230489],"iteration":144,"passed_time":0.2541728853,"remaining_time":1.498743565},
{"learn":[5.025976187],"iteration":145,"passed_time":0.2548455539,"remaining_time":1.490671938},
{"learn":[5.01952451],"iteration":146,"passed_time":0.2553982735,"remaining_time":1.482004948},
{"learn":[5.017569424],"iteration":147,"passed_time":0.2558951045,"remaining_time":1.473125872},
{"learn":[5.008962367],"iteration":148,"passed_time":0.2564283841,"remaining_time":1.464567482},
{"learn":[5.003880266],"iteration":149,"passed_time":0.2569680891,"remaining_time":1.456152505},
{"learn":[4.996387564],"iteration":150,"passed_time":0.2575146531,"remaining_time":1.4478804},
{"learn":[4.993361683],"iteration":151,"passed_time":0.2580325972,"remaining_time":1.439550279},
{"learn":[4.99005752],"iteration":152,"passed_time":0.2586240373,"remaining_time":1.431729148},
{"learn":[4.986908764],"iteration":153,"passed_time":0.2591452585,"remaining_time":1.42361616},
{"learn":[4.985207175],"iteration":154,"passed_time":0.2597226641,"remaining_time":1.415907427},
{"learn":[4.979003494],"iteration":155,"passed_time":0.2603175429,"remaining_time":1.408384655},
{"learn":[4.973142217],"iteration":156,"passed_time":0.2608495841,"remaining_time":1.400612735},
{"learn":[4.967056696],"iteration":157,"passed_time":0.2615537383,"remaining_time":1.393849669},
{"learn":[4.961460696],"iteration":158,"passed_time":0.2622484317,"remaining_time":1.387112774},
{"learn":[4.954240363],"iteration":159,"passed_time":0.2629856346,"remaining_time":1.380674582},
{"learn":[4.952320707],"iteration":160,"passed_time":0.2633896723,"remaining_time":1.372571025},
{"learn":[4.948337777],"iteration":161,"passed_time":0.2640129989,"remaining_time":1.365696871},
{"learn":[4.943228639],"iteration":162,"passed_time":0.2646426548,"remaining_time":1.358931915},
{"learn":[4.938545759],"iteration":163,"passed_time":0.2652670563,"remaining_time":1.352214994},
{"learn":[4.935330572],"iteration":164,"passed_time":0.2659071681,"remaining_time":1.345651427},
{"learn":[4.932051543],"iteration":165,"passed_time":0.2665550585,"remaining_time":1.339198306},
{"learn":[4.928964153],"iteration":166,"passed_time":0.2671606442,"remaining_time":1.332603692},
{"learn":[4.922860227],"iteration":167,"passed_time":0.2677346152,"remaining_time":1.325923808},
{"learn":[4.917668772],"iteration":168,"passed_time":0.2683066714,"remaining_time":1.319306769},
{"learn":[4.910365386],"iteration":169,"passed_time":0.2688602473,"remaining_time":1.312670619},
{"learn":[4.906457206],"iteration":170,"passed_time":0.2695552258,"remaining_time":1.306791124},
{"learn":[4.901996508],"iteration":171,"passed_time":0.2701069796,"remaining_time":1.300282436},
{"learn":[4.896816173],"iteration":172,"passed_time":0.2707276357,"remaining_time":1.294171993},
{"learn":[4.891123132],"iteration":173,"passed_time":0.2712800766,"remaining_time":1.287800824},
{"learn":[4.887630202],"iteration":174,"passed_time":0.2718673472,"remaining_time":1.281660351},
{"learn":[4.885259712],"iteration":175,"passed_time":0.2724245675,"remaining_time":1.275442293},
{"learn":[4.880659728],"iteration":176,"passed_time":0.2729358672,"remaining_time":1.269074682},
{"learn":[4.877299723],"iteration":177,"passed_time":0.2734655863,"remaining_time":1.262857932},
{"learn":[4.874038772],"iteration":178,"passed_time":0.2740349419,"remaining_time":1.256886521},
{"learn":[4.86943698],"iteration":179,"passed_time":0.274511843,"remaining_time":1.250553951},
{"learn":[4.861268711],"iteration":180,"passed_time":0.2750685168,"remaining_time":1.244647046},
{"learn":[4.858673056],"iteration":181,"passed_time":0.2757167833,"remaining_time":1.239210597},
{"learn":[4.854036207],"iteration":182,"passed_time":0.2765822094,"remaining_time":1.234795984},
{"learn":[4.85130244],"iteration":183,"passed_time":0.2771515081,"remaining_time":1.229106688},
{"learn":[4.847510084],"iteration":184,"passed_time":0.277667118,"remaining_time":1.223236223},
{"learn":[4.845691673],"iteration":185,"passed_time":0.278224354,"remaining_time":1.217605506},
{"learn":[4.842058646],"iteration":186,"passed_time":0.2788179919,"remaining_time":1.212187313},
{"learn":[4.838623675],"iteration":187,"passed_time":0.2794244668,"remaining_time":1.206875889},
{"learn":[4.834602161],"iteration":188,"passed_time":0.2800283847,"remaining_time":1.20160328},
{"learn":[4.830858976],"iteration":189,"passed_time":0.2806050562,"remaining_time":1.196263661},
{"learn":[4.827590511],"iteration":190,"passed_time":0.2811861792,"remaining_time":1.190992769},
{"learn":[4.822246226],"iteration":191,"passed_time":0.2817561125,"remaining_time":1.18572364},
{"learn":[4.816686395],"iteration":192,"passed_time":0.2822685741,"remaining_time":1.180262898},
{"learn":[4.814797121],"iteration":193,"passed_time":0.2828219681,"remaining_time":1.175023228},
{"learn":[4.811639392],"iteration":194,"passed_time":0.2834052347,"remaining_time":1.169954943},
{"learn":[4.804813432],"iteration":195,"passed_time":0.2839953229,"remaining_time":1.164960406},
{"learn":[4.80251613],"iteration":196,"passed_time":0.284576771,"remaining_time":1.159975366},
{"learn":[4.800087884],"iteration":197,"passed_time":0.2852069445,"remaining_time":1.155232169},
{"learn":[4.794773135],"iteration":198,"passed_time":0.2858093854,"remaining_time":1.150418682},
{"learn":[4.791664833],"iteration":199,"passed_time":0.2863543148,"remaining_time":1.145417259},
{"learn":[4.785989873],"iteration":200,"passed_time":0.2869405438,"remaining_time":1.140624351},
{"learn":[4.782387142],"iteration":201,"passed_time":0.2875414179,"remaining_time":1.135930948},
{"learn":[4.778623704],"iteration":202,"passed_time":0.2880964203,"remaining_time":1.131097768},
{"learn":[4.775772178],"iteration":203,"passed_time":0.2885947861,"remaining_time":1.126085538},
{"learn":[4.77023101],"iteration":204,"passed_time":0.2891827314,"remaining_time":1.121464739},
{"learn":[4.764496689],"iteration":205,"passed_time":0.2898027372,"remaining_time":1.117006667},
{"learn":[4.763138716],"iteration":206,"passed_time":0.2903491765,"remaining_time":1.11230385},
{"learn":[4.758053283],"iteration":207,"passed_time":0.291002484,"remaining_time":1.10804792},
{"learn":[4.755063788],"iteration":208,"passed_time":0.2916520527,"remaining_time":1.103812314},
{"learn":[4.752465267],"iteration":209,"passed_time":0.292272993,"remaining_time":1.099503164},
{"learn":[4.748067377],"iteration":210,"passed_time":0.2929664404,"remaining_time":1.095500102},
{"learn":[4.744163298],"iteration":211,"passed_time":0.2935459075,"remaining_time":1.0911046},
{"learn":[4.736670896],"iteration":212,"passed_time":0.2940918604,"remaining_time":1.086621099},
{"learn":[4.73349255],"iteration":213,"passed_time":0.294694592,"remaining_time":1.082382941},
{"learn":[4.731864595],"iteration":214,"passed_time":0.2951774659,"remaining_time":1.07774098},
{"learn":[4.728398311],"iteration":215,"passed_time":0.2957723343,"remaining_time":1.073544028},
{"learn":[4.723865975],"iteration":216,"passed_time":0.2962992549,"remaining_time":1.0691351},
{"learn":[4.723483365],"iteration":217,"passed_time":0.2968301747,"remaining_time":1.064776131},
{"learn":[4.72095416],"iteration":218,"passed_time":0.297404573,"remaining_time":1.060607176},
{"learn":[4.716173382],"iteration":219,"passed_time":0.2979992863,"remaining_time":1.056542924},
{"learn":[4.710563974],"iteration":220,"passed_time":0.2985429002,"remaining_time":1.052329952},
{"learn":[4.707160263],"iteration":221,"passed_time":0.2991233789,"remaining_time":1.048279229},
{"learn":[4.70408351],"iteration":222,"passed_time":0.2996848365,"remaining_time":1.044193354},
{"learn":[4.702501831],"iteration":223,"passed_time":0.3002816196,"remaining_time":1.040261325},
{"learn":[4.700269738],"iteration":224,"passed_time":0.3008814554,"remaining_time":1.036369457},
{"learn":[4.695346302],"iteration":225,"passed_time":0.3015155991,"remaining_time":1.03262422},
{"learn":[4.689769299],"iteration":226,"passed_time":0.3021239447,"remaining_time":1.028818543},
{"learn":[4.687919514],"iteration":227,"passed_time":0.3027306565,"remaining_time":1.025035381},
{"learn":[4.682982074],"iteration":228,"passed_time":0.3033192433,"remaining_time":1.021218937},
{"learn":[4.679578702],"iteration":229,"passed_time":0.3038603833,"remaining_time":1.017271718},
{"learn":[4.675751423],"iteration":230,"passed_time":0.3044218745,"remaining_time":1.013421738},
{"learn":[4.672710726],"iteration":231,"passed_time":0.3052636201,"remaining_time":1.010527846},
{"learn":[4.6690533],"iteration":232,"passed_time":0.3059758644,"remaining_time":1.00722527},
{"learn":[4.667595702],"iteration":233,"passed_time":0.3067635592,"remaining_time":1.004191822},
{"learn":[4.664241291],"iteration":234,"passed_time":0.3074154074,"remaining_time":1.000735262},
{"learn":[4.662246999],"iteration":235,"passed_time":0.3081921291,"remaining_time":0.9977067231},
{"learn":[4.658668443],"iteration":236,"passed_time":0.3088379275,"remaining_time":0.9942756907},
{"learn":[4.658017572],"iteration":237,"passed_time":0.3095025718,"remaining_time":0.9909284022},
{"learn":[4.657656705],"iteration":238,"passed_time":0.310112928,"remaining_time":0.9874307037},
{"learn":[4.653242871],"iteration":239,"passed_time":0.3106611501,"remaining_time":0.9837603087},
{"learn":[4.6507302],"iteration":240,"passed_time":0.3112442223,"remaining_time":0.9802255798},
{"learn":[4.647671336],"iteration":241,"passed_time":0.3117906884,"remaining_time":0.976600586},
{"learn":[4.645506007],"iteration":242,"passed_time":0.3123568716,"remaining_time":0.9730623531},
{"learn":[4.641297906],"iteration":243,"passed_time":0.3129827312,"remaining_time":0.9697333803},
{"learn":[4.63798107],"iteration":244,"passed_time":0.3135716853,"remaining_time":0.9663127444},
{"learn":[4.635062318],"iteration":245,"passed_time":0.3140357758,"remaining_time":0.9625324186},
{"learn":[4.631606017],"iteration":246,"passed_time":0.3145697819,"remaining_time":0.958992088},
{"learn":[4.630215494],"iteration":247,"passed_time":0.3151065073,"remaining_time":0.955484248},
{"learn":[4.62729814],"iteration":248,"passed_time":0.3156638114,"remaining_time":0.9520623388},
{"learn":[4.624691756],"iteration":249,"passed_time":0.3162289935,"remaining_time":0.9486869805},
{"learn":[4.621840053],"iteration":250,"passed_time":0.3167408292,"remaining_time":0.9451748251},
{"learn":[4.619602091],"iteration":251,"passed_time":0.3172803635,"remaining_time":0.941768698},
{"learn":[4.613584029],"iteration":252,"passed_time":0.3178091476,"remaining_time":0.9383534911},
{"learn":[4.6119388],"iteration":253,"passed_time":0.3183283057,"remaining_time":0.9349327402},
{"learn":[4.60870702],"iteration":254,"passed_time":0.3188452779,"remaining_time":0.931528361},
{"learn":[4.604771557],"iteration":255,"passed_time":0.3193309775,"remaining_time":0.9280556534},
{"learn":[4.604231277],"iteration":256,"passed_time":0.3199323099,"remaining_time":0.9249404912},
{"learn":[4.600750354],"iteration":257,"passed_time":0.3204205537,"remaining_time":0.9215195768},
{"learn":[4.596488253],"iteration":258,"passed_time":0.3209684342,"remaining_time":0.9182919295},
{"learn":[4.59470784],"iteration":259,"passed_time":0.3216161133,"remaining_time":0.9153689379},
{"learn":[4.588818005],"iteration":260,"passed_time":0.3222099425,"remaining_time":0.91231091},
{"learn":[4.585054174],"iteration":261,"passed_time":0.3227962709,"remaining_time":0.9092505647},
{"learn":[4.581471435],"iteration":262,"passed_time":0.3233584377,"remaining_time":0.9061413256},
{"learn":[4.577555199],"iteration":263,"passed_time":0.3238674418,"remaining_time":0.9029031711},
{"learn":[4.57457145],"iteration":264,"passed_time":0.324369425,"remaining_time":0.8996661411},
{"learn":[4.573029224],"iteration":265,"passed_time":0.32488425,"remaining_time":0.8964851109},
{"learn":[4.571326203],"iteration":266,"passed_time":0.3254678233,"remaining_time":0.8935127884},
{"learn":[4.571019224],"iteration":267,"passed_time":0.3259956324,"remaining_time":0.890405981},
{"learn":[4.565766631],"iteration":268,"passed_time":0.3265636931,"remaining_time":0.887427731},
{"learn":[4.563383471],"iteration":269,"passed_time":0.3270997502,"remaining_time":0.8843808061},
{"learn":[4.558165805],"iteration":270,"passed_time":0.3276580157,"remaining_time":0.8814121529},
{"learn":[4.55629209],"iteration":271,"passed_time":0.3281734015,"remaining_time":0.878346457},
{"learn":[4.549383848],"iteration":272,"passed_time":0.3287248979,"remaining_time":0.8753956073},
{"learn":[4.546227503],"iteration":273,"passed_time":0.3292707402,"remaining_time":0.8724472898},
{"learn":[4.540620977],"iteration":274,"passed_time":0.3297996197,"remaining_time":0.8694717247},
{"learn":[4.532898237],"iteration":275,"passed_time":0.3303342712,"remaining_time":0.8665290303},
{"learn":[4.529757367],"iteration":276,"passed_time":0.3308836203,"remaining_time":0.8636420848},
{"learn":[4.52579294],"iteration":277,"passed_time":0.3314221763,"remaining_time":0.8607439256},
{"learn":[4.521572155],"iteration":278,"passed_time":0.3319485722,"remaining_time":0.8578312564},
{"learn":[4.518818099],"iteration":279,"passed_time":0.3324922836,"remaining_time":0.8549801578},
{"learn":[4.514012334],"iteration":280,"passed_time":0.3330070552,"remaining_time":0.8520714332},
{"learn":[4.508331416],"iteration":281,"passed_time":0.3335406615,"remaining_time":0.8492276418},
{"learn":[4.506038537],"iteration":282,"passed_time":0.3340543146,"remaining_time":0.846349624},
{"learn":[4.505805643],"iteration":283,"passed_time":0.3345895206,"remaining_time":0.8435425942},
{"learn":[4.501550352],"iteration":284,"passed_time":0.3350934715,"remaining_time":0.8406730952},
{"learn":[4.494692643],"iteration":285,"passed_time":0.3359033743,"remaining_time":0.8385839484},
{"learn":[4.489330245],"iteration":286,"passed_time":0.3365884749,"remaining_time":0.8361936677},
{"learn":[4.484826955],"iteration":287,"passed_time":0.3372048212,"remaining_time":0.8336452524},
{"learn":[4.478285428],"iteration":288,"passed_time":0.3377431708,"remaining_time":0.8309183198},
{"learn":[4.475311671],"iteration":289,"passed_time":0.3383756692,"remaining_time":0.8284369831},
{"learn":[4.471581298],"iteration":290,"passed_time":0.3390516686,"remaining_time":0.8260743403},
{"learn":[4.469164956],"iteration":291,"passed_time":0.3396101714,"remaining_time":0.8234383608},
{"learn":[4.462068024],"iteration":292,"passed_time":0.3403147282,"remaining_time":0.8211689857},
{"learn":[4.458540976],"iteration":293,"passed_time":0.3409040077,"remaining_time":0.8186334336},
{"learn":[4.455757458],"iteration":294,"passed_time":0.3415015073,"remaining_time":0.8161307209},
{"learn":[4.453027414],"iteration":295,"passed_time":0.3420836907,"remaining_time":0.8136044535},
{"learn":[4.450659338],"iteration":296,"passed_time":0.3426813562,"remaining_time":0.811127924},
{"learn":[4.444696901],"iteration":297,"passed_time":0.3432981339,"remaining_time":0.8087090268},
{"learn":[4.442052813],"iteration":298,"passed_time":0.3438985862,"remaining_time":0.8062639095},
{"learn":[4.440036756],"iteration":299,"passed_time":0.3445057651,"remaining_time":0.8038467853},
{"learn":[4.435017051],"iteration":300,"passed_time":0.3450770239,"remaining_time":0.8013582715},
{"learn":[4.429962125],"iteration":301,"passed_time":0.3455928528,"remaining_time":0.7987543419},
{"learn":[4.427666256],"iteration":302,"passed_time":0.3461190413,"remaining_time":0.7961880258},
{"learn":[4.425030004],"iteration":303,"passed_time":0.3467030509,"remaining_time":0.7937675112},
{"learn":[4.422588771],"iteration":304,"passed_time":0.3473060655,"remaining_time":0.7914023459},
{"learn":[4.418936667],"iteration":305,"passed_time":0.3478799607,"remaining_time":0.7889826559},
{"learn":[4.416887976],"iteration":306,"passed_time":0.3484641334,"remaining_time":0.7865981904},
{"learn":[4.413773354],"iteration":307,"passed_time":0.349001344,"remaining_time":0.7841199026},
{"learn":[4.411129391],"iteration":308,"passed_time":0.3495727539,"remaining_time":0.7817306567},
{"learn":[4.40850819],"iteration":309,"passed_time":0.3501236172,"remaining_time":0.7793074061},
{"learn":[4.404880292],"iteration":310,"passed_time":0.3507105639,"remaining_time":0.7769761367},
{"learn":[4.404593827],"iteration":311,"passed_time":0.351456219,"remaining_time":0.7750060214},
{"learn":[4.402139942],"iteration":312,"passed_time":0.3524575963,"remaining_time":0.7736050117},
{"learn":[4.400284725],"iteration":313,"passed_time":0.3533249544,"remaining_time":0.7719137539},
{"learn":[4.395805521],"iteration":314,"passed_time":0.3540102836,"remaining_time":0.7698318865},
{"learn":[4.392838833],"iteration":315,"passed_time":0.3545744153,"remaining_time":0.7674965192},
{"learn":[4.389213061],"iteration":316,"passed_time":0.3551077987,"remaining_time":0.7651060773},
{"learn":[4.3861981],"iteration":317,"passed_time":0.3556052223,"remaining_time":0.7626501937},
{"learn":[4.385054234],"iteration":318,"passed_time":0.3562269697,"remaining_time":0.7604719949},
{"learn":[4.379364607],"iteration":319,"passed_time":0.3567905425,"remaining_time":0.7581799028},
{"learn":[4.378387619],"iteration":320,"passed_time":0.3573221378,"remaining_time":0.7558309395},
{"learn":[4.375816727],"iteration":321,"passed_time":0.3578531598,"remaining_time":0.753492057},
{"learn":[4.374600202],"iteration":322,"passed_time":0.3584085018,"remaining_time":0.7512153428},
{"learn":[4.37098897],"iteration":323,"passed_time":0.3589134177,"remaining_time":0.7488440444},
{"learn":[4.367418484],"iteration":324,"passed_time":0.3594392932,"remaining_time":0.7465277628},
{"learn":[4.363584638],"iteration":325,"passed_time":0.3599443286,"remaining_time":0.7441793787},
{"learn":[4.360770706],"iteration":326,"passed_time":0.3604703732,"remaining_time":0.7418855081},
{"learn":[4.358675808],"iteration":327,"passed_time":0.3610134211,"remaining_time":0.739637253},
{"learn":[4.354228195],"iteration":328,"passed_time":0.361508786,"remaining_time":0.7373021136},
{"learn":[4.353773425],"iteration":329,"passed_time":0.3619988624,"remaining_time":0.7349673872},
{"learn":[4.351648009],"iteration":330,"passed_time":0.3625028357,"remaining_time":0.7326718946},
{"learn":[4.348209927],"iteration":331,"passed_time":0.3630053674,"remaining_time":0.7303842934},
{"learn":[4.345852733],"iteration":332,"passed_time":0.3635260329,"remaining_time":0.7281437356},
{"learn":[4.34237339],"iteration":333,"passed_time":0.3640769885,"remaining_time":0.7259738753},
{"learn":[4.340814362],"iteration":334,"passed_time":0.3645850933,"remaining_time":0.7237286181},
{"learn":[4.339707068],"iteration":335,"passed_time":0.3653334389,"remaining_time":0.7219684627},
{"learn":[4.335430786],"iteration":336,"passed_time":0.3659000996,"remaining_time":0.7198568726},
{"learn":[4.33521887],"iteration":337,"passed_time":0.3664553711,"remaining_time":0.7177321173},
{"learn":[4.328507238],"iteration":338,"passed_time":0.3671016975,"remaining_time":0.7157941653},
{"learn":[4.326140732],"iteration":339,"passed_time":0.3676480822,"remaining_time":0.7136698066},
{"learn":[4.323785636],"iteration":340,"passed_time":0.3682244446,"remaining_time":0.7116126364},
{"learn":[4.320632534],"iteration":341,"passed_time":0.3687411018,"remaining_time":0.7094492544},
{"learn":[4.31973724],"iteration":342,"passed_time":0.3692304137,"remaining_time":0.7072430955},
{"learn":[4.318000924],"iteration":343,"passed_time":0.3698216144,"remaining_time":0.7052412182},
{"learn":[4.312713628],"iteration":344,"passed_time":0.3703248241,"remaining_time":0.7030804631},
{"learn":[4.308220789],"iteration":345,"passed_time":0.3708355268,"remaining_time":0.7009434524},
{"learn":[4.305890947],"iteration":346,"passed_time":0.3713445682,"remaining_time":0.6988126888},
{"learn":[4.305137856],"iteration":347,"passed_time":0.3718640321,"remaining_time":0.6967107728},
{"learn":[4.304787172],"iteration":348,"passed_time":0.3724078514,"remaining_time":0.694663356},
{"learn":[4.30350134],"iteration":349,"passed_time":0.3729185686,"remaining_time":0.6925630559},
{"learn":[4.30293809],"iteration":350,"passed_time":0.3733863508,"remaining_time":0.6903924264},
{"learn":[4.299548459],"iteration":351,"passed_time":0.3738807936,"remaining_time":0.6882805518},
{"learn":[4.294768408],"iteration":352,"passed_time":0.3744136766,"remaining_time":0.6862482968},
{"learn":[4.294581479],"iteration":353,"passed_time":0.374946192,"remaining_time":0.684223842},
{"learn":[4.292551604],"iteration":354,"passed_time":0.3754670725,"remaining_time":0.6821866528},
{"learn":[4.288628894],"iteration":355,"passed_time":0.376013276,"remaining_time":0.6802037914},
{"learn":[4.287802767],"iteration":356,"passed_time":0.376551027,"remaining_time":0.6782137544},
{"learn":[4.284566905],"iteration":357,"passed_time":0.377131862,"remaining_time":0.6763090934},
{"learn":[4.27890232],"iteration":358,"passed_time":0.3777004507,"remaining_time":0.6743899413},
{"learn":[4.276938023],"iteration":359,"passed_time":0.3781972914,"remaining_time":0.6723507402},
{"learn":[4.273425094],"iteration":360,"passed_time":0.3787122851,"remaining_time":0.6703522166},
{"learn":[4.269726505],"iteration":361,"passed_time":0.3792383081,"remaining_time":0.6683813276},
{"learn":[4.265565857],"iteration":362,"passed_time":0.3797757372,"remaining_time":0.6664384148},
{"learn":[4.262117173],"iteration":363,"passed_time":0.3802897759,"remaining_time":0.6644623558},
{"learn":[4.259185148],"iteration":364,"passed_time":0.3809266724,"remaining_time":0.6627080465},
{"learn":[4.257668507],"iteration":365,"passed_time":0.381574414,"remaining_time":0.6609786298},
{"learn":[4.253432436],"iteration":366,"passed_time":0.3822295101,"remaining_time":0.6592677926},
{"learn":[4.250216667],"iteration":367,"passed_time":0.3829813569,"remaining_time":0.6577288521},
{"learn":[4.24514828],"iteration":368,"passed_time":0.3836335375,"remaining_time":0.6560237457},
{"learn":[4.244015772],"iteration":369,"passed_time":0.3841938236,"remaining_time":0.6541678618},
{"learn":[4.240329192],"iteration":370,"passed_time":0.384805569,"remaining_time":0.6524062072},
{"learn":[4.236718014],"iteration":371,"passed_time":0.3853580051,"remaining_time":0.6505506108},
{"learn":[4.233495944],"iteration":372,"passed_time":0.3858999565,"remaining_time":0.6486843773},
{"learn":[4.230357491],"iteration":373,"passed_time":0.3864509574,"remaining_time":0.6468403725},
{"learn":[4.227381215],"iteration":374,"passed_time":0.3870063455,"remaining_time":0.6450105758},
{"learn":[4.226169067],"iteration":375,"passed_time":0.3875184138,"remaining_time":0.6431156654},
{"learn":[4.225963861],"iteration":376,"passed_time":0.3881128632,"remaining_time":0.6413642275},
{"learn":[4.224346548],"iteration":377,"passed_time":0.3886718752,"remaining_time":0.6395605988},
{"learn":[4.222595381],"iteration":378,"passed_time":0.3891762378,"remaining_time":0.6376739939},
{"learn":[4.219700938],"iteration":379,"passed_time":0.3897339368,"remaining_time":0.6358816864},
{"learn":[4.216356207],"iteration":380,"passed_time":0.3902959817,"remaining_time":0.6341029204},
{"learn":[4.214326494],"iteration":381,"passed_time":0.3908364064,"remaining_time":0.6322955476},
{"learn":[4.212901398],"iteration":382,"passed_time":0.39135815,"remaining_time":0.630464696},
{"learn":[4.211331091],"iteration":383,"passed_time":0.3918491429,"remaining_time":0.6285913334},
{"learn":[4.208624791],"iteration":384,"passed_time":0.3924035424,"remaining_time":0.6268264378},
{"learn":[4.204659106],"iteration":385,"passed_time":0.3930345217,"remaining_time":0.6251896277},
{"learn":[4.202968852],"iteration":386,"passed_time":0.3935771254,"remaining_time":0.6234180306},
{"learn":[4.197261935],"iteration":387,"passed_time":0.3940727392,"remaining_time":0.6215786505},
{"learn":[4.196934403],"iteration":388,"passed_time":0.3945473214,"remaining_time":0.6197131449},
{"learn":[4.192479929],"iteration":389,"passed_time":0.3951338186,"remaining_time":0.6180298188},
{"learn":[4.190243116],"iteration":390,"passed_time":0.395920018,"remaining_time":0.6166631482},
{"learn":[4.185852431],"iteration":391,"passed_time":0.3966024646,"remaining_time":0.6151385165},
{"learn":[4.180967944],"iteration":392,"passed_time":0.3975454584,"remaining_time":0.6140205935},
{"learn":[4.178283162],"iteration":393,"passed_time":0.398125296,"remaining_time":0.6123449984},
{"learn":[4.176341157],"iteration":394,"passed_time":0.3987319966,"remaining_time":0.6107160961},
{"learn":[4.176041504],"iteration":395,"passed_time":0.399232314,"remaining_time":0.6089300951},
{"learn":[4.175564513],"iteration":396,"passed_time":0.3997377058,"remaining_time":0.6071582786},
{"learn":[4.170830274],"iteration":397,"passed_time":0.4002329721,"remaining_time":0.6053775105},
{"learn":[4.167804808],"iteration":398,"passed_time":0.4007353069,"remaining_time":0.6036138332},
{"learn":[4.165860548],"iteration":399,"passed_time":0.4012870888,"remaining_time":0.6019306331},
{"learn":[4.160950571],"iteration":400,"passed_time":0.4018149515,"remaining_time":0.6002173466},
{"learn":[4.158544115],"iteration":401,"passed_time":0.4023391696,"remaining_time":0.5985045359},
{"learn":[4.154448767],"iteration":402,"passed_time":0.4029240852,"remaining_time":0.5968875406},
{"learn":[4.15197457],"iteration":403,"passed_time":0.4034357341,"remaining_time":0.5951675681},
{"learn":[4.149562679],"iteration":404,"passed_time":0.4039953804,"remaining_time":0.5935240773},
{"learn":[4.149327961],"iteration":405,"passed_time":0.4044738602,"remaining_time":0.5917671748},
{"learn":[4.147444889],"iteration":406,"passed_time":0.4050262792,"remaining_time":0.5901242839},
{"learn":[4.147254809],"iteration":407,"passed_time":0.4055540197,"remaining_time":0.5884509305},
{"learn":[4.144589165],"iteration":408,"passed_time":0.4060897035,"remaining_time":0.5867946572},
{"learn":[4.141691034],"iteration":409,"passed_time":0.4065593957,"remaining_time":0.5850488865},
{"learn":[4.138893468],"iteration":410,"passed_time":0.4070847495,"remaining_time":0.5833890936},
{"learn":[4.136964597],"iteration":411,"passed_time":0.4076557393,"remaining_time":0.5817999386},
{"learn":[4.133773523],"iteration":412,"passed_time":0.4081638574,"remaining_time":0.5801263542},
{"learn":[4.131363444],"iteration":413,"passed_time":0.4087089475,"remaining_time":0.5785107325},
{"learn":[4.130228592],"iteration":414,"passed_time":0.4092306787,"remaining_time":0.5768673422},
{"learn":[4.12884186],"iteration":415,"passed_time":0.4097426608,"remaining_time":0.5752156584},
{"learn":[4.12413494],"iteration":416,"passed_time":0.4102960335,"remaining_time":0.5736273082},
{"learn":[4.119422508],"iteration":417,"passed_time":0.4108587311,"remaining_time":0.5720568935},
{"learn":[4.117038244],"iteration":418,"passed_time":0.411431341,"remaining_time":0.5705050336},
{"learn":[4.116067631],"iteration":419,"passed_time":0.4119816298,"remaining_time":0.5689270126},
{"learn":[4.110343455],"iteration":420,"passed_time":0.4125670085,"remaining_time":0.5674021328},
{"learn":[4.105604544],"iteration":421,"passed_time":0.4130501314,"remaining_time":0.5657416491},
{"learn":[4.103390131],"iteration":422,"passed_time":0.4136146704,"remaining_time":0.5641977892},
{"learn":[4.096724402],"iteration":423,"passed_time":0.4141185395,"remaining_time":0.5625761292},
{"learn":[4.093431279],"iteration":424,"passed_time":0.4146934775,"remaining_time":0.5610558814},
{"learn":[4.091412744],"iteration":425,"passed_time":0.4152131692,"remaining_time":0.5594656318},
{"learn":[4.091192901],"iteration":426,"passed_time":0.4156995889,"remaining_time":0.557835748},
{"learn":[4.088994581],"iteration":427,"passed_time":0.4161973468,"remaining_time":0.5562263607},
{"learn":[4.087845355],"iteration":428,"passed_time":0.4167196405,"remaining_time":0.5546548128},
{"learn":[4.083650279],"iteration":429,"passed_time":0.4172194262,"remaining_time":0.5530583092},
{"learn":[4.079840652],"iteration":430,"passed_time":0.4177541559,"remaining_time":0.5515130272},
{"learn":[4.075707828],"iteration":431,"passed_time":0.4182815773,"remaining_time":0.5499628146},
{"learn":[4.071345409],"iteration":432,"passed_time":0.4188425462,"remaining_time":0.5484612556},
{"learn":[4.067460475],"iteration":433,"passed_time":0.4193451809,"remaining_time":0.5468879548},
{"learn":[4.064914749],"iteration":434,"passed_time":0.4198205681,"remaining_time":0.5452841861},
{"learn":[4.063823175],"iteration":435,"passed_time":0.4203184664,"remaining_time":0.5437147134},
{"learn":[4.058898471],"iteration":436,"passed_time":0.4208372572,"remaining_time":0.5421770613},
{"learn":[4.054120355],"iteration":437,"passed_time":0.4213791084,"remaining_time":0.5406736504},
{"learn":[4.052715901],"iteration":438,"passed_time":0.4218545834,"remaining_time":0.5390897979},
{"learn":[4.052114167],"iteration":439,"passed_time":0.4223806352,"remaining_time":0.5375753539},
{"learn":[4.051377267],"iteration":440,"passed_time":0.42290009,"remaining_time":0.5360570301},
{"learn":[4.049275336],"iteration":441,"passed_time":0.4234092841,"remaining_time":0.5345302726},
{"learn":[4.047099198],"iteration":442,"passed_time":0.4239298706,"remaining_time":0.5330224332},
{"learn":[4.044348685],"iteration":443,"passed_time":0.4244618043,"remaining_time":0.5315332504},
{"learn":[4.042822379],"iteration":444,"passed_time":0.4249695178,"remaining_time":0.5300181627},
{"learn":[4.041258611],"iteration":445,"passed_time":0.4256391627,"remaining_time":0.5287087358},
{"learn":[4.040044254],"iteration":446,"passed_time":0.4263534725,"remaining_time":0.527457428},
{"learn":[4.036860137],"iteration":447,"passed_time":0.4269820223,"remaining_time":0.5261028489},
{"learn":[4.036372284],"iteration":448,"passed_time":0.4276263353,"remaining_time":0.524770848},
{"learn":[4.03368231],"iteration":449,"passed_time":0.4281529356,"remaining_time":0.5232980324},
{"learn":[4.032439519],"iteration":450,"passed_time":0.4286668076,"remaining_time":0.5218139188},
{"learn":[4.032008634],"iteration":451,"passed_time":0.4291846751,"remaining_time":0.5203389424},
{"learn":[4.030034932],"iteration":452,"passed_time":0.4297301835,"remaining_time":0.5189015681},
{"learn":[4.028173412],"iteration":453,"passed_time":0.4302442222,"remaining_time":0.5174302761},
{"learn":[4.023806097],"iteration":454,"passed_time":0.4308420473,"remaining_time":0.5160635512},
{"learn":[4.020239186],"iteration":455,"passed_time":0.4313867795,"remaining_time":0.5146368597},
{"learn":[4.017384838],"iteration":456,"passed_time":0.4319116815,"remaining_time":0.5131904662},
{"learn":[4.016468229],"iteration":457,"passed_time":0.4324773892,"remaining_time":0.5117963864},
{"learn":[4.014530169],"iteration":458,"passed_time":0.4329886877,"remaining_time":0.5103417866},
{"learn":[4.012884822],"iteration":459,"passed_time":0.4335633651,"remaining_time":0.5089656895},
{"learn":[4.008924707],"iteration":460,"passed_time":0.4340609491,"remaining_time":0.5075029318},
{"learn":[4.008286778],"iteration":461,"passed_time":0.4345823868,"remaining_time":0.50607213},
{"learn":[4.006444202],"iteration":462,"passed_time":0.4350872626,"remaining_time":0.5046260475},
{"learn":[4.003284363],"iteration":463,"passed_time":0.4356256266,"remaining_time":0.5032227066},
{"learn":[3.999811484],"iteration":464,"passed_time":0.4361417942,"remaining_time":0.5017975482},
{"learn":[3.997483319],"iteration":465,"passed_time":0.4367361466,"remaining_time":0.5004658847},
{"learn":[3.99708333],"iteration":466,"passed_time":0.4372667464,"remaining_time":0.4990646164},
{"learn":[3.995860263],"iteration":467,"passed_time":0.4377841806,"remaining_time":0.4976521027},
{"learn":[3.994131111],"iteration":468,"passed_time":0.4382504834,"remaining_time":0.4961855153},
{"learn":[3.993125499],"iteration":469,"passed_time":0.4387692334,"remaining_time":0.494782327},
{"learn":[3.992954084],"iteration":470,"passed_time":0.4392521241,"remaining_time":0.4933426193},
{"learn":[3.990635743],"iteration":471,"passed_time":0.4397366583,"remaining_time":0.4919088042},
{"learn":[3.986678254],"iteration":472,"passed_time":0.440295817,"remaining_time":0.490562147},
{"learn":[3.986393291],"iteration":473,"passed_time":0.4409452128,"remaining_time":0.4893189492},
{"learn":[3.986152671],"iteration":474,"passed_time":0.4415615222,"remaining_time":0.4880416824},
{"learn":[3.985596662],"iteration":475,"passed_time":0.4421759112,"remaining_time":0.4867650787},
{"learn":[3.983853457],"iteration":476,"passed_time":0.4427715509,"remaining_time":0.4854706942},
{"learn":[3.983263928],"iteration":477,"passed_time":0.4433504359,"remaining_time":0.4841609363},
{"learn":[3.980067202],"iteration":478,"passed_time":0.4439934901,"remaining_time":0.4829240257},
{"learn":[3.978115407],"iteration":479,"passed_time":0.44463506,"remaining_time":0.4816879817},
{"learn":[3.972661644],"iteration":480,"passed_time":0.4451792898,"remaining_time":0.4803493792},
{"learn":[3.969938254],"iteration":481,"passed_time":0.4457207557,"remaining_time":0.4790111026},
{"learn":[3.968211434],"iteration":482,"passed_time":0.4462368107,"remaining_time":0.4776489257},
{"learn":[3.966113368],"iteration":483,"passed_time":0.4467940021,"remaining_time":0.4763341014},
{"learn":[3.962246044],"iteration":484,"passed_time":0.4473483546,"remaining_time":0.4750193869},
{"learn":[3.961319703],"iteration":485,"passed_time":0.4479427912,"remaining_time":0.4737501948},
{"learn":[3.96078191],"iteration":486,"passed_time":0.4484728903,"remaining_time":0.4724160015},
{"learn":[3.958913633],"iteration":487,"passed_time":0.4489957039,"remaining_time":0.4710774599},
{"learn":[3.957428286],"iteration":488,"passed_time":0.4495662523,"remaining_time":0.4697921369},
{"learn":[3.952641965],"iteration":489,"passed_time":0.4500923687,"remaining_time":0.4684634858},
{"learn":[3.951486786],"iteration":490,"passed_time":0.4506744566,"remaining_time":0.4671961271},
{"learn":[3.94938344],"iteration":491,"passed_time":0.4512082754,"remaining_time":0.4658817153},
{"learn":[3.947297924],"iteration":492,"passed_time":0.4517472877,"remaining_time":0.4645758111},
{"learn":[3.946284886],"iteration":493,"passed_time":0.4523203037,"remaining_time":0.4633078414},
{"learn":[3.943288204],"iteration":494,"passed_time":0.4528959581,"remaining_time":0.4620453714},
{"learn":[3.943076488],"iteration":495,"passed_time":0.4534242876,"remaining_time":0.4607375825},
{"learn":[3.942347078],"iteration":496,"passed_time":0.4539598051,"remaining_time":0.4594402051},
{"learn":[3.940251541],"iteration":497,"passed_time":0.4545643275,"remaining_time":0.4582154466},
{"learn":[3.939011019],"iteration":498,"passed_time":0.455135802,"remaining_time":0.4569599936},
{"learn":[3.938760512],"iteration":499,"passed_time":0.4557014163,"remaining_time":0.4557014163},
{"learn":[3.934522727],"iteration":500,"passed_time":0.4563349598,"remaining_time":0.4545132634},
{"learn":[3.930091193],"iteration":501,"passed_time":0.4569456893,"remaining_time":0.4533046878},
{"learn":[3.927671752],"iteration":502,"passed_time":0.4575208979,"remaining_time":0.4520633921},
{"learn":[3.927280041],"iteration":503,"passed_time":0.4581407895,"remaining_time":0.4508687134},
{"learn":[3.925987561],"iteration":504,"passed_time":0.4587289208,"remaining_time":0.4496451798},
{"learn":[3.921645957],"iteration":505,"passed_time":0.4593179891,"remaining_time":0.4484250724},
{"learn":[3.920333743],"iteration":506,"passed_time":0.459872405,"remaining_time":0.4471737587},
{"learn":[3.918659461],"iteration":507,"passed_time":0.4603391529,"remaining_time":0.4458402819},
{"learn":[3.916124385],"iteration":508,"passed_time":0.4609244057,"remaining_time":0.4446245249},
{"learn":[3.913849268],"iteration":509,"passed_time":0.4614334911,"remaining_time":0.4433380601},
{"learn":[3.912826119],"iteration":510,"passed_time":0.4619757267,"remaining_time":0.4420863608},
{"learn":[3.910034145],"iteration":511,"passed_time":0.4625191146,"remaining_time":0.4408385311},
{"learn":[3.90792379],"iteration":512,"passed_time":0.4630978573,"remaining_time":0.4396270107},
{"learn":[3.907823851],"iteration":513,"passed_time":0.4636309509,"remaining_time":0.4383747901},
{"learn":[3.904527401],"iteration":514,"passed_time":0.4641298883,"remaining_time":0.4370931958},
{"learn":[3.903378283],"iteration":515,"passed_time":0.4646762305,"remaining_time":0.4358591},
{"learn":[3.902170135],"iteration":516,"passed_time":0.4652525437,"remaining_time":0.4346556646},
{"learn":[3.899435429],"iteration":517,"passed_time":0.4658209439,"remaining_time":0.4334472876},
{"learn":[3.897497505],"iteration":518,"passed_time":0.4664010574,"remaining_time":0.4322522324},
{"learn":[3.896426119],"iteration":519,"passed_time":0.4672680053,"remaining_time":0.4313243126},
{"learn":[3.896044669],"iteration":520,"passed_time":0.4678750363,"remaining_time":0.4301576629},
{"learn":[3.892795942],"iteration":521,"passed_time":0.4684641591,"remaining_time":0.4289767588},
{"learn":[3.892413888],"iteration":522,"passed_time":0.4689824168,"remaining_time":0.4277334853},
{"learn":[3.891738985],"iteration":523,"passed_time":0.4695605064,"remaining_time":0.4265473302},
{"learn":[3.88822057],"iteration":524,"passed_time":0.4701790649,"remaining_time":0.4254001063},
{"learn":[3.883837053],"iteration":525,"passed_time":0.470816333,"remaining_time":0.4242717525},
{"learn":[3.881769742],"iteration":526,"passed_time":0.4713862559,"remaining_time":0.4230848179},
{"learn":[3.880356898],"iteration":527,"passed_time":0.4720750839,"remaining_time":0.4220065144},
{"learn":[3.879250273],"iteration":528,"passed_time":0.4726699735,"remaining_time":0.4208460445},
{"learn":[3.877174493],"iteration":529,"passed_time":0.4731992932,"remaining_time":0.4196295619},
{"learn":[3.875854201],"iteration":530,"passed_time":0.4737865999,"remaining_time":0.4184668839},
{"learn":[3.873189396],"iteration":531,"passed_time":0.4743135606,"remaining_time":0.4172532826},
{"learn":[3.871583368],"iteration":532,"passed_time":0.4748687146,"remaining_time":0.4160669601},
{"learn":[3.869622679],"iteration":533,"passed_time":0.4753500334,"remaining_time":0.4148185684},
{"learn":[3.866860164],"iteration":534,"passed_time":0.4758158391,"remaining_time":0.4135595611},
{"learn":[3.864498444],"iteration":535,"passed_time":0.4763012119,"remaining_time":0.4123204521},
{"learn":[3.861416322],"iteration":536,"passed_time":0.4767691814,"remaining_time":0.4110691452},
{"learn":[3.860265769],"iteration":537,"passed_time":0.4772870128,"remaining_time":0.4098635686},
{"learn":[3.859328725],"iteration":538,"passed_time":0.4777825677,"remaining_time":0.4086414911},
{"learn":[3.858521278],"iteration":539,"passed_time":0.4783120903,"remaining_time":0.4074510399},
{"learn":[3.85599111],"iteration":540,"passed_time":0.4788149808,"remaining_time":0.4062404366},
{"learn":[3.852379816],"iteration":541,"passed_time":0.479350123,"remaining_time":0.405059698},
{"learn":[3.851327537],"iteration":542,"passed_time":0.4798700007,"remaining_time":0.4038684905},
{"learn":[3.847854898],"iteration":543,"passed_time":0.4803489822,"remaining_time":0.4026454703},
{"learn":[3.847083414],"iteration":544,"passed_time":0.4808620479,"remaining_time":0.4014536363},
{"learn":[3.845397429],"iteration":545,"passed_time":0.4813765995,"remaining_time":0.4002655241},
{"learn":[3.841933528],"iteration":546,"passed_time":0.4819208389,"remaining_time":0.3991044607},
{"learn":[3.840996474],"iteration":547,"passed_time":0.4824433065,"remaining_time":0.3979276908},
{"learn":[3.838355966],"iteration":548,"passed_time":0.4829685208,"remaining_time":0.3967555608},
{"learn":[3.83342799],"iteration":549,"passed_time":0.4835173227,"remaining_time":0.3956050822},
{"learn":[3.828161535],"iteration":550,"passed_time":0.4840172352,"remaining_time":0.3944169484},
{"learn":[3.823502399],"iteration":551,"passed_time":0.4845677826,"remaining_time":0.3932724033},
{"learn":[3.820068862],"iteration":552,"passed_time":0.4850640195,"remaining_time":0.3920861062},
{"learn":[3.817951642],"iteration":553,"passed_time":0.4857091071,"remaining_time":0.3910221331},
{"learn":[3.815785958],"iteration":554,"passed_time":0.486340705,"remaining_time":0.3899488536},
{"learn":[3.81503012],"iteration":555,"passed_time":0.4870128139,"remaining_time":0.3889095133},
{"learn":[3.813529315],"iteration":556,"passed_time":0.4876173023,"remaining_time":0.3878177108},
{"learn":[3.808881326],"iteration":557,"passed_time":0.4882414059,"remaining_time":0.3867431925},
{"learn":[3.808740434],"iteration":558,"passed_time":0.4887878564,"remaining_time":0.3856090244},
{"learn":[3.80714352],"iteration":559,"passed_time":0.489282231,"remaining_time":0.3844360386},
{"learn":[3.80573346],"iteration":560,"passed_time":0.4897976577,"remaining_time":0.3832819461},
{"learn":[3.803370052],"iteration":561,"passed_time":0.4903258164,"remaining_time":0.3821400491},
{"learn":[3.803215211],"iteration":562,"passed_time":0.4908478803,"remaining_time":0.3809956016},
{"learn":[3.801309667],"iteration":563,"passed_time":0.4914174236,"remaining_time":0.379890065},
{"learn":[3.800003847],"iteration":564,"passed_time":0.4919815974,"remaining_time":0.3787822918},
{"learn":[3.798026138],"iteration":565,"passed_time":0.4925129525,"remaining_time":0.3776512746},
{"learn":[3.794745847],"iteration":566,"passed_time":0.4930181427,"remaining_time":0.3765023912},
{"learn":[3.794312041],"iteration":567,"passed_time":0.4935677059,"remaining_time":0.3753895228},
{"learn":[3.792205926],"iteration":568,"passed_time":0.4940887711,"remaining_time":0.3742570481},
{"learn":[3.788991061],"iteration":569,"passed_time":0.4946313275,"remaining_time":0.3731429313},
{"learn":[3.787391572],"iteration":570,"passed_time":0.495191246,"remaining_time":0.3720438608},
{"learn":[3.7826445],"iteration":571,"passed_time":0.4957151549,"remaining_time":0.3709197313},
{"learn":[3.781700331],"iteration":572,"passed_time":0.4962609615,"remaining_time":0.3698140149},
{"learn":[3.780045374],"iteration":573,"passed_time":0.496778833,"remaining_time":0.3686895172},
{"learn":[3.775462644],"iteration":574,"passed_time":0.4973030262,"remaining_time":0.367571802},
{"learn":[3.773711943],"iteration":575,"passed_time":0.4977949136,"remaining_time":0.3664323669},
{"learn":[3.772415806],"iteration":576,"passed_time":0.4982937696,"remaining_time":0.3653002852},
{"learn":[3.770170875],"iteration":577,"passed_time":0.4987900193,"remaining_time":0.3641684916},
{"learn":[3.765166479],"iteration":578,"passed_time":0.4993189453,"remaining_time":0.3630626528},
{"learn":[3.763976102],"iteration":579,"passed_time":0.4998399573,"remaining_time":0.3619530725},
{"learn":[3.760761708],"iteration":580,"passed_time":0.5005224804,"remaining_time":0.3609619953},
{"learn":[3.758155662],"iteration":581,"passed_time":0.5012991564,"remaining_time":0.3600396003},
{"learn":[3.756844548],"iteration":582,"passed_time":0.5020977301,"remaining_time":0.3591333678},
{"learn":[3.753098923],"iteration":583,"passed_time":0.5027462351,"remaining_time":0.3581206058},
{"learn":[3.751618946],"iteration":584,"passed_time":0.5033647455,"remaining_time":0.3570878109},
{"learn":[3.751398464],"iteration":585,"passed_time":0.5039293515,"remaining_time":0.3560183473},
{"learn":[3.749920103],"iteration":586,"passed_time":0.5044368096,"remaining_time":0.3549103959},
{"learn":[3.748237465],"iteration":587,"passed_time":0.5049767167,"remaining_time":0.3538272233},
{"learn":[3.746021536],"iteration":588,"passed_time":0.5055184853,"remaining_time":0.3527471943},
{"learn":[3.74417648],"iteration":589,"passed_time":0.506027244,"remaining_time":0.3516460509},
{"learn":[3.738788389],"iteration":590,"passed_time":0.5065506237,"remaining_time":0.3505570306},
{"learn":[3.736021611],"iteration":591,"passed_time":0.507137756,"remaining_time":0.3495138589},
{"learn":[3.734546151],"iteration":592,"passed_time":0.5076409191,"remaining_time":0.3484145937},
{"learn":[3.733527479],"iteration":593,"passed_time":0.5081756231,"remaining_time":0.3473388939},
{"learn":[3.733026392],"iteration":594,"passed_time":0.5086612253,"remaining_time":0.3462315903},
{"learn":[3.730314752],"iteration":595,"passed_time":0.5091563035,"remaining_time":0.3451327963},
{"learn":[3.727342596],"iteration":596,"passed_time":0.5097121547,"remaining_time":0.3440770491},
{"learn":[3.725459604],"iteration":597,"passed_time":0.5102204415,"remaining_time":0.3429909991},
{"learn":[3.723158842],"iteration":598,"passed_time":0.5107387777,"remaining_time":0.3419136058},
{"learn":[3.722362756],"iteration":599,"passed_time":0.5112791743,"remaining_time":0.3408527829},
{"learn":[3.721443615],"iteration":600,"passed_time":0.5118121568,"remaining_time":0.3397887697},
{"learn":[3.720743486],"iteration":601,"passed_time":0.5123071537,"remaining_time":0.3387014072},
{"learn":[3.720215334],"iteration":602,"passed_time":0.5128194673,"remaining_time":0.3376274105},
{"learn":[3.719436563],"iteration":603,"passed_time":0.5133993638,"remaining_time":0.3365995829},
{"learn":[3.715046574],"iteration":604,"passed_time":0.5138703734,"remaining_time":0.3355021446},
{"learn":[3.71443396],"iteration":605,"passed_time":0.5144408557,"remaining_time":0.3344714474},
{"learn":[3.712938941],"iteration":606,"passed_time":0.5149707066,"remaining_time":0.3334159599},
{"learn":[3.712814764],"iteration":607,"passed_time":0.5154863594,"remaining_time":0.3323530475},
{"learn":[3.71235348],"iteration":608,"passed_time":0.5160388313,"remaining_time":0.3313155715},
{"learn":[3.711223749],"iteration":609,"passed_time":0.5166766037,"remaining_time":0.3303342221},
{"learn":[3.710755648],"iteration":610,"passed_time":0.517380266,"remaining_time":0.3293959468},
{"learn":[3.708668039],"iteration":611,"passed_time":0.5180241966,"remaining_time":0.3284205691},
{"learn":[3.705623591],"iteration":612,"passed_time":0.5186099525,"remaining_time":0.3274095459},
{"learn":[3.704045802],"iteration":613,"passed_time":0.5191962549,"remaining_time":0.3264002514},
{"learn":[3.699915209],"iteration":614,"passed_time":0.5197842271,"remaining_time":0.3253933779},
{"learn":[3.696182221],"iteration":615,"passed_time":0.5203338151,"remaining_time":0.3243639367},
{"learn":[3.694263278],"iteration":616,"passed_time":0.5209039285,"remaining_time":0.3233487919},
{"learn":[3.693810229],"iteration":617,"passed_time":0.5214217395,"remaining_time":0.3223027581},
{"learn":[3.690900932],"iteration":618,"passed_time":0.5219283336,"remaining_time":0.3212515268},
{"learn":[3.688020895],"iteration":619,"passed_time":0.5224669149,"remaining_time":0.3202216575},
{"learn":[3.685491894],"iteration":620,"passed_time":0.5230401053,"remaining_time":0.3192144926},
{"learn":[3.684328128],"iteration":621,"passed_time":0.5235525124,"remaining_time":0.318171784},
{"learn":[3.680640153],"iteration":622,"passed_time":0.5240825397,"remaining_time":0.3171414406},
{"learn":[3.678932783],"iteration":623,"passed_time":0.5245982772,"remaining_time":0.3161040901},
{"learn":[3.674167041],"iteration":624,"passed_time":0.5250805357,"remaining_time":0.3150483214},
{"learn":[3.672200976],"iteration":625,"passed_time":0.5255710567,"remaining_time":0.3139993214},
{"learn":[3.670606604],"iteration":626,"passed_time":0.5261017207,"remaining_time":0.3129759837},
{"learn":[3.665506042],"iteration":627,"passed_time":0.5266229262,"remaining_time":0.3119486124},
{"learn":[3.664214007],"iteration":628,"passed_time":0.5271904822,"remaining_time":0.310950189},
{"learn":[3.66261643],"iteration":629,"passed_time":0.5277007752,"remaining_time":0.3099195029},
{"learn":[3.662118449],"iteration":630,"passed_time":0.5281918663,"remaining_time":0.3088792372},
{"learn":[3.660871366],"iteration":631,"passed_time":0.5287732679,"remaining_time":0.3078932952},
{"learn":[3.656695243],"iteration":632,"passed_time":0.5293530004,"remaining_time":0.3069076637},
{"learn":[3.654497801],"iteration":633,"passed_time":0.5299176657,"remaining_time":0.3059146146},
{"learn":[3.654189134],"iteration":634,"passed_time":0.5304863446,"remaining_time":0.3049252217},
{"learn":[3.653957699],"iteration":635,"passed_time":0.5309814217,"remaining_time":0.3038950275},
{"learn":[3.651920725],"iteration":636,"passed_time":0.5315881652,"remaining_time":0.3029301475},
{"learn":[3.65106705],"iteration":637,"passed_time":0.532144902,"remaining_time":0.3019380165},
{"learn":[3.650612844],"iteration":638,"passed_time":0.5327786047,"remaining_time":0.3009907297},
{"learn":[3.649884732],"iteration":639,"passed_time":0.5333869042,"remaining_time":0.3000301336},
{"learn":[3.646276182],"iteration":640,"passed_time":0.5340098672,"remaining_time":0.2990788492},
{"learn":[3.645808194],"iteration":641,"passed_time":0.5347594087,"remaining_time":0.2981991718},
{"learn":[3.645042989],"iteration":642,"passed_time":0.5353422805,"remaining_time":0.2972273626},
{"learn":[3.639864499],"iteration":643,"passed_time":0.5359983636,"remaining_time":0.296297232},
{"learn":[3.637318478],"iteration":644,"passed_time":0.5371798491,"remaining_time":0.2956571262},
{"learn":[3.636344905],"iteration":645,"passed_time":0.5377362222,"remaining_time":0.2946727905},
{"learn":[3.634754643],"iteration":646,"passed_time":0.5383055073,"remaining_time":0.2936968224},
{"learn":[3.630724975],"iteration":647,"passed_time":0.5388249544,"remaining_time":0.292695037},
{"learn":[3.629408252],"iteration":648,"passed_time":0.5396562297,"remaining_time":0.2918633846},
{"learn":[3.62790646],"iteration":649,"passed_time":0.5404114779,"remaining_time":0.2909907958},
{"learn":[3.627388973],"iteration":650,"passed_time":0.5410159005,"remaining_time":0.2900377101},
{"learn":[3.625163557],"iteration":651,"passed_time":0.5415784975,"remaining_time":0.2890633698},
{"learn":[3.623701985],"iteration":652,"passed_time":0.5421776536,"remaining_time":0.2881097179},
{"learn":[3.622342639],"iteration":653,"passed_time":0.543840793,"remaining_time":0.2877200526},
{"learn":[3.621130639],"iteration":654,"passed_time":0.5443959334,"remaining_time":0.2867428962},
{"learn":[3.619125665],"iteration":655,"passed_time":0.5449516639,"remaining_time":0.2857673359},
{"learn":[3.618878783],"iteration":656,"passed_time":0.5454501968,"remaining_time":0.2847631925},
{"learn":[3.616207429],"iteration":657,"passed_time":0.5459418147,"remaining_time":0.2837569918},
{"learn":[3.61206486],"iteration":658,"passed_time":0.5464841053,"remaining_time":0.2827785734},
{"learn":[3.611955873],"iteration":659,"passed_time":0.5469666829,"remaining_time":0.2817707154},
{"learn":[3.610713743],"iteration":660,"passed_time":0.5476046298,"remaining_time":0.2808441293},
{"learn":[3.610044025],"iteration":661,"passed_time":0.5482321496,"remaining_time":0.2799130915},
{"learn":[3.607342669],"iteration":662,"passed_time":0.5487753137,"remaining_time":0.2789400916},
{"learn":[3.602510618],"iteration":663,"passed_time":0.5493557507,"remaining_time":0.2779872474},
{"learn":[3.600492392],"iteration":664,"passed_time":0.5499427772,"remaining_time":0.2770388426},
{"learn":[3.597171065],"iteration":665,"passed_time":0.5504345326,"remaining_time":0.2760437446},
{"learn":[3.594358798],"iteration":666,"passed_time":0.5509513104,"remaining_time":0.2750626482},
{"learn":[3.593945251],"iteration":667,"passed_time":0.551417653,"remaining_time":0.2740578754},
{"learn":[3.593607748],"iteration":668,"passed_time":0.5519331162,"remaining_time":0.2730790156},
{"learn":[3.592238714],"iteration":669,"passed_time":0.5524643495,"remaining_time":0.2721093065},
{"learn":[3.590144654],"iteration":670,"passed_time":0.5529922784,"remaining_time":0.271139284},
{"learn":[3.587151536],"iteration":671,"passed_time":0.5534862353,"remaining_time":0.2701539958},
{"learn":[3.586070865],"iteration":672,"passed_time":0.5539787448,"remaining_time":0.2691694644},
{"learn":[3.585102746],"iteration":673,"passed_time":0.5545540092,"remaining_time":0.2682264199},
{"learn":[3.584362847],"iteration":674,"passed_time":0.5551027252,"remaining_time":0.2672716825},
{"learn":[3.581407561],"iteration":675,"passed_time":0.5556824265,"remaining_time":0.2663329973},
{"learn":[3.57919422],"iteration":676,"passed_time":0.5562182848,"remaining_time":0.2653744549},
{"learn":[3.577632204],"iteration":677,"passed_time":0.5567509914,"remaining_time":0.2644156626},
{"learn":[3.573911195],"iteration":678,"passed_time":0.5572692667,"remaining_time":0.2634513028},
{"learn":[3.573408216],"iteration":679,"passed_time":0.5578177001,"remaining_time":0.2625024471},
{"learn":[3.571076482],"iteration":680,"passed_time":0.5583066355,"remaining_time":0.2615268968},
{"learn":[3.568177107],"iteration":681,"passed_time":0.55882898,"remaining_time":0.2605683514},
{"learn":[3.564824621],"iteration":682,"passed_time":0.5593755829,"remaining_time":0.2596223423},
{"learn":[3.562475026],"iteration":683,"passed_time":0.5599682045,"remaining_time":0.2586987611},
{"learn":[3.561226889],"iteration":684,"passed_time":0.5605218991,"remaining_time":0.2577582456},
{"learn":[3.559383467],"iteration":685,"passed_time":0.5611163493,"remaining_time":0.2568375127},
{"learn":[3.555209766],"iteration":686,"passed_time":0.5617833823,"remaining_time":0.2559507986},
{"learn":[3.55345383],"iteration":687,"passed_time":0.5624465075,"remaining_time":0.2550629511},
{"learn":[3.552300968],"iteration":688,"passed_time":0.5630572173,"remaining_time":0.2541520966},
{"learn":[3.551253986],"iteration":689,"passed_time":0.5636191054,"remaining_time":0.2532201778},
{"learn":[3.549807725],"iteration":690,"passed_time":0.5641956331,"remaining_time":0.2522958764},
{"learn":[3.547992926],"iteration":691,"passed_time":0.5647513227,"remaining_time":0.2513633055},
{"learn":[3.545438607],"iteration":692,"passed_time":0.565295698,"remaining_time":0.2504268099},
{"learn":[3.543313763],"iteration":693,"passed_time":0.5658723203,"remaining_time":0.2495056628},
{"learn":[3.542962896],"iteration":694,"passed_time":0.5663961217,"remaining_time":0.2485623268},
{"learn":[3.539800465],"iteration":695,"passed_time":0.5669017308,"remaining_time":0.2476122503},
{"learn":[3.53953187],"iteration":696,"passed_time":0.5674534935,"remaining_time":0.2466835129},
{"learn":[3.536332425],"iteration":697,"passed_time":0.5679988442,"remaining_time":0.2457530816},
{"learn":[3.534993327],"iteration":698,"passed_time":0.5684922695,"remaining_time":0.2448013921},
{"learn":[3.531637011],"iteration":699,"passed_time":0.569001375,"remaining_time":0.2438577321},
{"learn":[3.531040284],"iteration":700,"passed_time":0.5694862455,"remaining_time":0.2429049749},
{"learn":[3.529973872],"iteration":701,"passed_time":0.5700680002,"remaining_time":0.2419946782},
{"learn":[3.527325183],"iteration":702,"passed_time":0.5705964095,"remaining_time":0.241062779},
{"learn":[3.527200815],"iteration":703,"passed_time":0.5710734292,"remaining_time":0.2401104191},
{"learn":[3.523459911],"iteration":704,"passed_time":0.5716505911,"remaining_time":0.2392013112},
{"learn":[3.522729934],"iteration":705,"passed_time":0.5721847659,"remaining_time":0.2382752425},
{"learn":[3.522260582],"iteration":706,"passed_time":0.5726709526,"remaining_time":0.2373303948},
{"learn":[3.518641591],"iteration":707,"passed_time":0.5731753477,"remaining_time":0.2363943525},
{"learn":[3.516856405],"iteration":708,"passed_time":0.5737014762,"remaining_time":0.2354684479},
{"learn":[3.515083413],"iteration":709,"passed_time":0.5742613333,"remaining_time":0.234557446},
{"learn":[3.514671214],"iteration":710,"passed_time":0.5747561545,"remaining_time":0.2336209967},
{"learn":[3.512617621],"iteration":711,"passed_time":0.5753107508,"remaining_time":0.2327099666},
{"learn":[3.510747971],"iteration":712,"passed_time":0.5760478223,"remaining_time":0.2318733871},
{"learn":[3.508149266],"iteration":713,"passed_time":0.5766575514,"remaining_time":0.230986078},
{"learn":[3.504557165],"iteration":714,"passed_time":0.5772951306,"remaining_time":0.2301106465},
{"learn":[3.501367208],"iteration":715,"passed_time":0.5778535906,"remaining_time":0.2292044968},
{"learn":[3.497593362],"iteration":716,"passed_time":0.5784141377,"remaining_time":0.2283001408},
{"learn":[3.496291169],"iteration":717,"passed_time":0.579043308,"remaining_time":0.2274236948},
{"learn":[3.49330374],"iteration":718,"passed_time":0.5794978019,"remaining_time":0.2264796694},
{"learn":[3.490044385],"iteration":719,"passed_time":0.5801061719,"remaining_time":0.2255968446},
{"learn":[3.488891789],"iteration":720,"passed_time":0.5805943251,"remaining_time":0.2246682617},
{"learn":[3.486869081],"iteration":721,"passed_time":0.5811574998,"remaining_time":0.2237697853},
{"learn":[3.486303638],"iteration":722,"passed_time":0.5817110505,"remaining_time":0.2228685491},
{"learn":[3.486035862],"iteration":723,"passed_time":0.5822428058,"remaining_time":0.2219599646},
{"learn":[3.482668951],"iteration":724,"passed_time":0.5828164248,"remaining_time":0.2210682991},
{"learn":[3.47820549],"iteration":725,"passed_time":0.5833737032,"remaining_time":0.2201713425},
{"learn":[3.474392283],"iteration":726,"passed_time":0.583972851,"remaining_time":0.2192910431},
{"learn":[3.472268163],"iteration":727,"passed_time":0.5845223644,"remaining_time":0.2183929713},
{"learn":[3.471209164],"iteration":728,"passed_time":0.5850462301,"remaining_time":0.2174863215},
{"learn":[3.470049971],"iteration":729,"passed_time":0.5855579023,"remaining_time":0.2165762104},
{"learn":[3.469078654],"iteration":730,"passed_time":0.5860723913,"remaining_time":0.2156682261},
{"learn":[3.468643292],"iteration":731,"passed_time":0.5865461568,"remaining_time":0.2147464071},
{"learn":[3.468134848],"iteration":732,"passed_time":0.5871167324,"remaining_time":0.2138610744},
{"learn":[3.467820182],"iteration":733,"passed_time":0.5876101252,"remaining_time":0.2129486285},
{"learn":[3.465776156],"iteration":734,"passed_time":0.5880987338,"remaining_time":0.2120355979},
{"learn":[3.463037608],"iteration":735,"passed_time":0.5886193544,"remaining_time":0.2111352032},
{"learn":[3.45965637],"iteration":736,"passed_time":0.5891136268,"remaining_time":0.2102264367},
{"learn":[3.457275091],"iteration":737,"passed_time":0.5896547495,"remaining_time":0.209335426},
{"learn":[3.455522955],"iteration":738,"passed_time":0.5901755962,"remaining_time":0.2084382011},
{"learn":[3.451270508],"iteration":739,"passed_time":0.5906912852,"remaining_time":0.2075401813},
{"learn":[3.450978947],"iteration":740,"passed_time":0.5912486787,"remaining_time":0.2066577703},
{"learn":[3.450608492],"iteration":741,"passed_time":0.5919751102,"remaining_time":0.2058350114},
{"learn":[3.448122004],"iteration":742,"passed_time":0.5927614615,"remaining_time":0.2050332377},
{"learn":[3.445646714],"iteration":743,"passed_time":0.5933513714,"remaining_time":0.2041639127},
{"learn":[3.44411263],"iteration":744,"passed_time":0.5939513542,"remaining_time":0.2032987857},
{"learn":[3.443264164],"iteration":745,"passed_time":0.5946677993,"remaining_time":0.2024740228},
{"learn":[3.439521363],"iteration":746,"passed_time":0.5953760942,"remaining_time":0.2016467896},
{"learn":[3.436809225],"iteration":747,"passed_time":0.5959672513,"remaining_time":0.2007804109},
{"learn":[3.435509465],"iteration":748,"passed_time":0.5965019994,"remaining_time":0.1998958636},
{"learn":[3.434450277],"iteration":749,"passed_time":0.5971628194,"remaining_time":0.1990542731},
{"learn":[3.431786753],"iteration":750,"passed_time":0.5977959672,"remaining_time":0.1982039891},
{"learn":[3.430150302],"iteration":751,"passed_time":0.5985997035,"remaining_time":0.1974105405},
{"learn":[3.42696281],"iteration":752,"passed_time":0.5992429661,"remaining_time":0.1965644258},
{"learn":[3.426870334],"iteration":753,"passed_time":0.5998718951,"remaining_time":0.1957141727},
{"learn":[3.425200309],"iteration":754,"passed_time":0.6005638783,"remaining_time":0.1948849671},
{"learn":[3.423383783],"iteration":755,"passed_time":0.6011482475,"remaining_time":0.194021392},
{"learn":[3.422752979],"iteration":756,"passed_time":0.6016638703,"remaining_time":0.1931364868},
{"learn":[3.420845924],"iteration":757,"passed_time":0.6022028581,"remaining_time":0.1922600154},
{"learn":[3.418917862],"iteration":758,"passed_time":0.6027534845,"remaining_time":0.1913881288},
{"learn":[3.417095735],"iteration":759,"passed_time":0.6033692414,"remaining_time":0.1905376552},
{"learn":[3.414391848],"iteration":760,"passed_time":0.6040611881,"remaining_time":0.1897117266},
{"learn":[3.41426711],"iteration":761,"passed_time":0.6046367528,"remaining_time":0.1888497994},
{"learn":[3.411976013],"iteration":762,"passed_time":0.6052541843,"remaining_time":0.1880016274},
{"learn":[3.408614844],"iteration":763,"passed_time":0.6059541538,"remaining_time":0.1871795554},
{"learn":[3.407906721],"iteration":764,"passed_time":0.6064769169,"remaining_time":0.1863033666},
{"learn":[3.407494015],"iteration":765,"passed_time":0.6071172849,"remaining_time":0.185464027},
{"learn":[3.406287128],"iteration":766,"passed_time":0.6076864874,"remaining_time":0.1846035874},
{"learn":[3.404600442],"iteration":767,"passed_time":0.608241511,"remaining_time":0.1837396231},
{"learn":[3.404012662],"iteration":768,"passed_time":0.6088488379,"remaining_time":0.1828921737},
{"learn":[3.400398762],"iteration":769,"passed_time":0.6094312762,"remaining_time":0.1820379137},
{"learn":[3.399737714],"iteration":770,"passed_time":0.6099677258,"remaining_time":0.1811706994},
{"learn":[3.399185251],"iteration":771,"passed_time":0.6105220792,"remaining_time":0.1803096296},
{"learn":[3.397245411],"iteration":772,"passed_time":0.6110694582,"remaining_time":0.1794473053},
{"learn":[3.396229831],"iteration":773,"passed_time":0.6115811376,"remaining_time":0.1785753709},
{"learn":[3.394002836],"iteration":774,"passed_time":0.6121047201,"remaining_time":0.177707822},
{"learn":[3.389617243],"iteration":775,"passed_time":0.6126510143,"remaining_time":0.1768477155},
{"learn":[3.385426488],"iteration":776,"passed_time":0.613151658,"remaining_time":0.175975315},
{"learn":[3.385072258],"iteration":777,"passed_time":0.6137015812,"remaining_time":0.1751179319},
{"learn":[3.383842366],"iteration":778,"passed_time":0.6143013564,"remaining_time":0.1742754811},
{"learn":[3.380110746],"iteration":779,"passed_time":0.6148133593,"remaining_time":0.1734088962},
{"learn":[3.378595218],"iteration":780,"passed_time":0.6153888273,"remaining_time":0.1725610156},
{"learn":[3.377371219],"iteration":781,"passed_time":0.6159499838,"remaining_time":0.171709842},
{"learn":[3.375814782],"iteration":782,"passed_time":0.6164972205,"remaining_time":0.1708555515},
{"learn":[3.374195887],"iteration":783,"passed_time":0.6170744914,"remaining_time":0.1700103191},
{"learn":[3.373704309],"iteration":784,"passed_time":0.6176185132,"remaining_time":0.1691566628},
{"learn":[3.372971757],"iteration":785,"passed_time":0.6181643687,"remaining_time":0.1683042938},
{"learn":[3.371565136],"iteration":786,"passed_time":0.6187461764,"remaining_time":0.167462434},
{"learn":[3.3700309],"iteration":787,"passed_time":0.6193258809,"remaining_time":0.1666206685},
{"learn":[3.368186663],"iteration":788,"passed_time":0.6198418212,"remaining_time":0.1657625149},
{"learn":[3.366710398],"iteration":789,"passed_time":0.6204708244,"remaining_time":0.1649352824},
{"learn":[3.364598042],"iteration":790,"passed_time":0.621124563,"remaining_time":0.1641150868},
{"learn":[3.36348442],"iteration":791,"passed_time":0.6218675243,"remaining_time":0.1633187438},
{"learn":[3.362001759],"iteration":792,"passed_time":0.6226817549,"remaining_time":0.1625411391},
{"learn":[3.361580401],"iteration":793,"passed_time":0.6234480697,"remaining_time":0.1617510105},
{"learn":[3.359543675],"iteration":794,"passed_time":0.624252862,"remaining_time":0.1609708638},
{"learn":[3.35766119],"iteration":795,"passed_time":0.6250331691,"remaining_time":0.16018438},
{"learn":[3.354592969],"iteration":796,"passed_time":0.6257008483,"remaining_time":0.1593692248},
{"learn":[3.350985986],"iteration":797,"passed_time":0.6263689272,"remaining_time":0.1585545405},
{"learn":[3.349589624],"iteration":798,"passed_time":0.6269160977,"remaining_time":0.1577098068},
{"learn":[3.349110856],"iteration":799,"passed_time":0.6275470309,"remaining_time":0.1568867577},
{"learn":[3.345315441],"iteration":800,"passed_time":0.6281899836,"remaining_time":0.1560671745},
{"learn":[3.34397474],"iteration":801,"passed_time":0.6287281243,"remaining_time":0.1552221554},
{"learn":[3.343800902],"iteration":802,"passed_time":0.6292630132,"remaining_time":0.1543771029},
{"learn":[3.342329465],"iteration":803,"passed_time":0.6298179827,"remaining_time":0.1535377172},
{"learn":[3.34220347],"iteration":804,"passed_time":0.6304153604,"remaining_time":0.1527093109},
{"learn":[3.341279219],"iteration":805,"passed_time":0.6310001153,"remaining_time":0.1518784397},
{"learn":[3.337329521],"iteration":806,"passed_time":0.6315143757,"remaining_time":0.1510313191},
{"learn":[3.336708453],"iteration":807,"passed_time":0.6320155591,"remaining_time":0.150181915},
{"learn":[3.333252703],"iteration":808,"passed_time":0.6325887632,"remaining_time":0.1493503755},
{"learn":[3.332186769],"iteration":809,"passed_time":0.633174149,"remaining_time":0.1485223313},
{"learn":[3.330594851],"iteration":810,"passed_time":0.633784136,"remaining_time":0.1477006186},
{"learn":[3.327867442],"iteration":811,"passed_time":0.6343893997,"remaining_time":0.1468783339},
{"learn":[3.327563111],"iteration":812,"passed_time":0.6349501986,"remaining_time":0.1460463556},
{"learn":[3.326308994],"iteration":813,"passed_time":0.6354156086,"remaining_time":0.1451932472},
{"learn":[3.326249879],"iteration":814,"passed_time":0.6359515494,"remaining_time":0.1443571002},
{"learn":[3.322336238],"iteration":815,"passed_time":0.6365238165,"remaining_time":0.1435298802},
{"learn":[3.320491154],"iteration":816,"passed_time":0.6373024229,"remaining_time":0.1427495023},
{"learn":[3.320434271],"iteration":817,"passed_time":0.6380033742,"remaining_time":0.141951851},
{"learn":[3.319609638],"iteration":818,"passed_time":0.6385764355,"remaining_time":0.141126172},
{"learn":[3.316182682],"iteration":819,"passed_time":0.6391456958,"remaining_time":0.1403002747},
{"learn":[3.313126612],"iteration":820,"passed_time":0.6397386742,"remaining_time":0.1394801738},
{"learn":[3.311222803],"iteration":821,"passed_time":0.6402962746,"remaining_time":0.1386529646},
{"learn":[3.309627335],"iteration":822,"passed_time":0.6408875006,"remaining_time":0.1378336423},
{"learn":[3.307974895],"iteration":823,"passed_time":0.6414822178,"remaining_time":0.1370156193},
{"learn":[3.307321505],"iteration":824,"passed_time":0.6420775276,"remaining_time":0.1361982634},
{"learn":[3.306759087],"iteration":825,"passed_time":0.6426296278,"remaining_time":0.1353723429},
{"learn":[3.30484037],"iteration":826,"passed_time":0.6431806972,"remaining_time":0.1345468689},
{"learn":[3.30201994],"iteration":827,"passed_time":0.6437731994,"remaining_time":0.1337306646},
{"learn":[3.299302297],"iteration":828,"passed_time":0.6443614771,"remaining_time":0.1329141286},
{"learn":[3.298132671],"iteration":829,"passed_time":0.644981171,"remaining_time":0.1321045772},
{"learn":[3.296976183],"iteration":830,"passed_time":0.6455892548,"remaining_time":0.1312931216},
{"learn":[3.293144745],"iteration":831,"passed_time":0.646158335,"remaining_time":0.1304742792},
{"learn":[3.290284404],"iteration":832,"passed_time":0.6466876439,"remaining_time":0.1296480631},
{"learn":[3.288285745],"iteration":833,"passed_time":0.6472650547,"remaining_time":0.1288321332},
{"learn":[3.286662667],"iteration":834,"passed_time":0.6477917605,"remaining_time":0.1280067551},
{"learn":[3.285692682],"iteration":835,"passed_time":0.6483141407,"remaining_time":0.1271812429},
{"learn":[3.284565611],"iteration":836,"passed_time":0.6489645625,"remaining_time":0.1263813903},
{"learn":[3.283897383],"iteration":837,"passed_time":0.6494708636,"remaining_time":0.1255540333},
{"learn":[3.280712855],"iteration":838,"passed_time":0.6500193647,"remaining_time":0.1247355396},
{"learn":[3.280468341],"iteration":839,"passed_time":0.6505743246,"remaining_time":0.123918919},
{"learn":[3.277814895],"iteration":840,"passed_time":0.6512370321,"remaining_time":0.1231232914},
{"learn":[3.276316385],"iteration":841,"passed_time":0.6519594589,"remaining_time":0.1223391859},
{"learn":[3.27557063],"iteration":842,"passed_time":0.652663229,"remaining_time":0.121551752},
{"learn":[3.27499628],"iteration":843,"passed_time":0.6534002748,"remaining_time":0.1207706669},
{"learn":[3.273569958],"iteration":844,"passed_time":0.6541173077,"remaining_time":0.119986015},
{"learn":[3.269665595],"iteration":845,"passed_time":0.6547118774,"remaining_time":0.1191792306},
{"learn":[3.267984685],"iteration":846,"passed_time":0.6552439698,"remaining_time":0.1183616616},
{"learn":[3.267702508],"iteration":847,"passed_time":0.6558046897,"remaining_time":0.1175498972},
{"learn":[3.266671924],"iteration":848,"passed_time":0.6563755035,"remaining_time":0.1167405195},
{"learn":[3.265359825],"iteration":849,"passed_time":0.656889978,"remaining_time":0.1159217608},
{"learn":[3.2618983],"iteration":850,"passed_time":0.6574553638,"remaining_time":0.1151126313},
{"learn":[3.260456253],"iteration":851,"passed_time":0.6579887664,"remaining_time":0.1142985181},
{"learn":[3.258389147],"iteration":852,"passed_time":0.6585117902,"remaining_time":0.1134832745},
{"learn":[3.258108469],"iteration":853,"passed_time":0.6590275685,"remaining_time":0.1126674766},
{"learn":[3.256424936],"iteration":854,"passed_time":0.6595209986,"remaining_time":0.1118485904},
{"learn":[3.254817983],"iteration":855,"passed_time":0.6600671327,"remaining_time":0.1110393307},
{"learn":[3.253898449],"iteration":856,"passed_time":0.6605805798,"remaining_time":0.1102252309},
{"learn":[3.253023652],"iteration":857,"passed_time":0.6611324246,"remaining_time":0.1094181868},
{"learn":[3.252845542],"iteration":858,"passed_time":0.6616947401,"remaining_time":0.1086134556},
{"learn":[3.252316026],"iteration":859,"passed_time":0.6621995646,"remaining_time":0.1077999291},
{"learn":[3.24975301],"iteration":860,"passed_time":0.6626522195,"remaining_time":0.1069786974},
{"learn":[3.249151075],"iteration":861,"passed_time":0.6631788089,"remaining_time":0.1061701573},
{"learn":[3.246257135],"iteration":862,"passed_time":0.663717211,"remaining_time":0.1053641459},
{"learn":[3.243826471],"iteration":863,"passed_time":0.6643266459,"remaining_time":0.104569935},
{"learn":[3.243190653],"iteration":864,"passed_time":0.6647976571,"remaining_time":0.1037545476},
{"learn":[3.24008797],"iteration":865,"passed_time":0.6653210163,"remaining_time":0.1029480556},
{"learn":[3.240036811],"iteration":866,"passed_time":0.6659882257,"remaining_time":0.1021642838},
{"learn":[3.238676314],"iteration":867,"passed_time":0.6667654369,"remaining_time":0.1013975088},
{"learn":[3.237848782],"iteration":868,"passed_time":0.6674503652,"remaining_time":0.1006167984},
{"learn":[3.236405498],"iteration":869,"passed_time":0.6680811994,"remaining_time":0.09982822519},
{"learn":[3.233378068],"iteration":870,"passed_time":0.668729291,"remaining_time":0.09904257008},
{"learn":[3.233169169],"iteration":871,"passed_time":0.6692372663,"remaining_time":0.09823666295},
{"learn":[3.232434885],"iteration":872,"passed_time":0.6697710037,"remaining_time":0.09743518611},
{"learn":[3.229978115],"iteration":873,"passed_time":0.6703871612,"remaining_time":0.09664620401},
{"learn":[3.229648848],"iteration":874,"passed_time":0.6709388027,"remaining_time":0.09584840039},
{"learn":[3.227208761],"iteration":875,"passed_time":0.6714456723,"remaining_time":0.09504482119},
{"learn":[3.226258869],"iteration":876,"passed_time":0.6719472329,"remaining_time":0.09424117406},
{"learn":[3.225331995],"iteration":877,"passed_time":0.6724380647,"remaining_time":0.09343672425},
{"learn":[3.221968268],"iteration":878,"passed_time":0.6729848046,"remaining_time":0.09264068414},
{"learn":[3.221166317],"iteration":879,"passed_time":0.673535963,"remaining_time":0.09184581314},
{"learn":[3.220047503],"iteration":880,"passed_time":0.6740977654,"remaining_time":0.09105293313},
{"learn":[3.21982781],"iteration":881,"passed_time":0.6746509685,"remaining_time":0.09025942663},
{"learn":[3.216693405],"iteration":882,"passed_time":0.6751944017,"remaining_time":0.08946516987},
{"learn":[3.214798761],"iteration":883,"passed_time":0.6756814175,"remaining_time":0.08866407741},
{"learn":[3.214395085],"iteration":884,"passed_time":0.6762147023,"remaining_time":0.08786970707},
{"learn":[3.213470696],"iteration":885,"passed_time":0.6767279733,"remaining_time":0.08707335096},
{"learn":[3.211595017],"iteration":886,"passed_time":0.6772877715,"remaining_time":0.08628356051},
{"learn":[3.210965255],"iteration":887,"passed_time":0.6778192569,"remaining_time":0.08549071709},
{"learn":[3.209413583],"iteration":888,"passed_time":0.6783418617,"remaining_time":0.08469735281},
{"learn":[3.208331683],"iteration":889,"passed_time":0.6788689078,"remaining_time":0.08390514591},
{"learn":[3.207110711],"iteration":890,"passed_time":0.6793875659,"remaining_time":0.08311250807},
{"learn":[3.204519413],"iteration":891,"passed_time":0.6799165653,"remaining_time":0.08232173661},
{"learn":[3.201421296],"iteration":892,"passed_time":0.6804288894,"remaining_time":0.08152955337},
{"learn":[3.200691259],"iteration":893,"passed_time":0.6810381539,"remaining_time":0.08074949028},
{"learn":[3.200485067],"iteration":894,"passed_time":0.6817840515,"remaining_time":0.07998583844},
{"learn":[3.197467568],"iteration":895,"passed_time":0.6825132862,"remaining_time":0.07922029215},
{"learn":[3.195838544],"iteration":896,"passed_time":0.6832958641,"remaining_time":0.07846095207},
{"learn":[3.195671746],"iteration":897,"passed_time":0.683898926,"remaining_time":0.07768116977},
{"learn":[3.194213094],"iteration":898,"passed_time":0.6844494971,"remaining_time":0.07689588344},
{"learn":[3.192884691],"iteration":899,"passed_time":0.6849917869,"remaining_time":0.07611019854},
{"learn":[3.188364239],"iteration":900,"passed_time":0.6855086333,"remaining_time":0.07532225826},
{"learn":[3.185219478],"iteration":901,"passed_time":0.6860516267,"remaining_time":0.07453775988},
{"learn":[3.184120387],"iteration":902,"passed_time":0.6866248495,"remaining_time":0.07375704364},
{"learn":[3.183725321],"iteration":903,"passed_time":0.6871372955,"remaining_time":0.07297033226},
{"learn":[3.181264554],"iteration":904,"passed_time":0.6876833931,"remaining_time":0.0721877595},
{"learn":[3.180741589],"iteration":905,"passed_time":0.6882284508,"remaining_time":0.07140560086},
{"learn":[3.179782639],"iteration":906,"passed_time":0.688729388,"remaining_time":0.07061944111},
{"learn":[3.176377564],"iteration":907,"passed_time":0.6892894208,"remaining_time":0.06983989726},
{"learn":[3.174078182],"iteration":908,"passed_time":0.6898051041,"remaining_time":0.06905639656},
{"learn":[3.171242379],"iteration":909,"passed_time":0.6903626451,"remaining_time":0.06827762424},
{"learn":[3.170421012],"iteration":910,"passed_time":0.6909317414,"remaining_time":0.0675004665},
{"learn":[3.170087224],"iteration":911,"passed_time":0.691512807,"remaining_time":0.06672491997},
{"learn":[3.167303059],"iteration":912,"passed_time":0.6920160178,"remaining_time":0.06594238067},
{"learn":[3.16705966],"iteration":913,"passed_time":0.6925183643,"remaining_time":0.06516037125},
{"learn":[3.165667683],"iteration":914,"passed_time":0.693023722,"remaining_time":0.06437925286},
{"learn":[3.164689733],"iteration":915,"passed_time":0.6935331013,"remaining_time":0.06359910536},
{"learn":[3.163311455],"iteration":916,"passed_time":0.6940816277,"remaining_time":0.06282309171},
{"learn":[3.159425016],"iteration":917,"passed_time":0.6946462698,"remaining_time":0.06204901321},
{"learn":[3.159327058],"iteration":918,"passed_time":0.6951825177,"remaining_time":0.06127288785},
{"learn":[3.15819426],"iteration":919,"passed_time":0.6957342387,"remaining_time":0.06049862945},
{"learn":[3.157086603],"iteration":920,"passed_time":0.6963281553,"remaining_time":0.05972847369},
{"learn":[3.153354154],"iteration":921,"passed_time":0.6969986341,"remaining_time":0.05896517729},
{"learn":[3.153261317],"iteration":922,"passed_time":0.6976288633,"remaining_time":0.05819872424},
{"learn":[3.153168454],"iteration":923,"passed_time":0.6982827037,"remaining_time":0.05743450809},
{"learn":[3.152080399],"iteration":924,"passed_time":0.698924903,"remaining_time":0.05666958673},
{"learn":[3.151635144],"iteration":925,"passed_time":0.6994986162,"remaining_time":0.05589945745},
{"learn":[3.147762655],"iteration":926,"passed_time":0.7000846095,"remaining_time":0.05513071898},
{"learn":[3.147172317],"iteration":927,"passed_time":0.7007940719,"remaining_time":0.05437195385},
{"learn":[3.146254125],"iteration":928,"passed_time":0.701311334,"remaining_time":0.05359860572},
{"learn":[3.144869828],"iteration":929,"passed_time":0.7018221562,"remaining_time":0.05282532359},
{"learn":[3.143466218],"iteration":930,"passed_time":0.7024280963,"remaining_time":0.05205965483},
{"learn":[3.141919643],"iteration":931,"passed_time":0.7029392084,"remaining_time":0.05128741005},
{"learn":[3.141054135],"iteration":932,"passed_time":0.7034290025,"remaining_time":0.05051419418},
{"learn":[3.139390417],"iteration":933,"passed_time":0.7039046792,"remaining_time":0.04974058761},
{"learn":[3.139025283],"iteration":934,"passed_time":0.7044419555,"remaining_time":0.04897190065},
{"learn":[3.137824183],"iteration":935,"passed_time":0.7049540013,"remaining_time":0.048201983},
{"learn":[3.135620453],"iteration":936,"passed_time":0.7054746576,"remaining_time":0.0474331947},
{"learn":[3.13443178],"iteration":937,"passed_time":0.706013285,"remaining_time":0.04666612332},
{"learn":[3.132765713],"iteration":938,"passed_time":0.7065729573,"remaining_time":0.04590090564},
{"learn":[3.131434124],"iteration":939,"passed_time":0.7071242805,"remaining_time":0.04513559237},
{"learn":[3.128384262],"iteration":940,"passed_time":0.7076502418,"remaining_time":0.04436914374},
{"learn":[3.128120455],"iteration":941,"passed_time":0.7081400387,"remaining_time":0.04360097903},
{"learn":[3.126314615],"iteration":942,"passed_time":0.7087030775,"remaining_time":0.04283783183},
{"learn":[3.125409666],"iteration":943,"passed_time":0.7092442415,"remaining_time":0.04207381094},
{"learn":[3.123072589],"iteration":944,"passed_time":0.7097725894,"remaining_time":0.04130951578},
{"learn":[3.122921099],"iteration":945,"passed_time":0.7103464501,"remaining_time":0.04054831745},
{"learn":[3.122182662],"iteration":946,"passed_time":0.7109921074,"remaining_time":0.03979153294},
{"learn":[3.120040951],"iteration":947,"passed_time":0.7115499271,"remaining_time":0.03903016478},
{"learn":[3.118767799],"iteration":948,"passed_time":0.7122611037,"remaining_time":0.03827746711},
{"learn":[3.118203218],"iteration":949,"passed_time":0.712867846,"remaining_time":0.03751936032},
{"learn":[3.116343362],"iteration":950,"passed_time":0.713490627,"remaining_time":0.03676239824},
{"learn":[3.11480829],"iteration":951,"passed_time":0.7140632381,"remaining_time":0.03600318848},
{"learn":[3.112607903],"iteration":952,"passed_time":0.7146651201,"remaining_time":0.0352458139},
{"learn":[3.111661241],"iteration":953,"passed_time":0.7151970365,"remaining_time":0.0344853917},
{"learn":[3.110249676],"iteration":954,"passed_time":0.7157215072,"remaining_time":0.0337250972},
{"learn":[3.107333579],"iteration":955,"passed_time":0.7162429352,"remaining_time":0.03296515602},
{"learn":[3.107149851],"iteration":956,"passed_time":0.7167834598,"remaining_time":0.03220657134},
{"learn":[3.106867336],"iteration":957,"passed_time":0.7173740904,"remaining_time":0.03145063862},
{"learn":[3.10364681],"iteration":958,"passed_time":0.717909371,"remaining_time":0.03069268426},
{"learn":[3.102703811],"iteration":959,"passed_time":0.7184586772,"remaining_time":0.02993577822},
{"learn":[3.101469264],"iteration":960,"passed_time":0.7189762757,"remaining_time":0.02917801743},
{"learn":[3.09863569],"iteration":961,"passed_time":0.7195020846,"remaining_time":0.02842108026},
{"learn":[3.09645939],"iteration":962,"passed_time":0.7200719478,"remaining_time":0.02766631575},
{"learn":[3.096240186],"iteration":963,"passed_time":0.7206146004,"remaining_time":0.02691091869},
{"learn":[3.094838828],"iteration":964,"passed_time":0.7211049297,"remaining_time":0.02615406481},
{"learn":[3.094176802],"iteration":965,"passed_time":0.7216247662,"remaining_time":0.02539880129},
{"learn":[3.093182279],"iteration":966,"passed_time":0.7221894423,"remaining_time":0.02464555491},
{"learn":[3.090150687],"iteration":967,"passed_time":0.7227007657,"remaining_time":0.0238909344},
{"learn":[3.088612829],"iteration":968,"passed_time":0.723238056,"remaining_time":0.02313764679},
{"learn":[3.087153684],"iteration":969,"passed_time":0.7237972147,"remaining_time":0.02238548087},
{"learn":[3.085866843],"iteration":970,"passed_time":0.7243433252,"remaining_time":0.02163332279},
{"learn":[3.082669094],"iteration":971,"passed_time":0.7248720299,"remaining_time":0.02088108728},
{"learn":[3.081047548],"iteration":972,"passed_time":0.725446403,"remaining_time":0.0201305785},
{"learn":[3.079684322],"iteration":973,"passed_time":0.7259823764,"remaining_time":0.01937940635},
{"learn":[3.07613431],"iteration":974,"passed_time":0.726544455,"remaining_time":0.018629345},
{"learn":[3.074005935],"iteration":975,"passed_time":0.7271736658,"remaining_time":0.01788131965},
{"learn":[3.072988853],"iteration":976,"passed_time":0.7277921606,"remaining_time":0.01713328526},
{"learn":[3.072344268],"iteration":977,"passed_time":0.7283297019,"remaining_time":0.01638369473},
{"learn":[3.070654438],"iteration":978,"passed_time":0.7289712819,"remaining_time":0.01563676907},
{"learn":[3.069724506],"iteration":979,"passed_time":0.7297244077,"remaining_time":0.01489233485},
{"learn":[3.067763166],"iteration":980,"passed_time":0.7304871249,"remaining_time":0.01414806868},
{"learn":[3.066737893],"iteration":981,"passed_time":0.7311746451,"remaining_time":0.01340238657},
{"learn":[3.065248174],"iteration":982,"passed_time":0.7317634717,"remaining_time":0.01265511599},
{"learn":[3.063186837],"iteration":983,"passed_time":0.7323513898,"remaining_time":0.01190815268},
{"learn":[3.062880371],"iteration":984,"passed_time":0.7328344521,"remaining_time":0.01115991551},
{"learn":[3.061288645],"iteration":985,"passed_time":0.7333483049,"remaining_time":0.01041265342},
{"learn":[3.059970575],"iteration":986,"passed_time":0.7339409265,"remaining_time":0.009666901767},
{"learn":[3.059576341],"iteration":987,"passed_time":0.7344422775,"remaining_time":0.008920351548},
{"learn":[3.058175919],"iteration":988,"passed_time":0.7349959376,"remaining_time":0.008174878983},
{"learn":[3.056830702],"iteration":989,"passed_time":0.7354794658,"remaining_time":0.007429085514},
{"learn":[3.056336579],"iteration":990,"passed_time":0.7360158637,"remaining_time":0.006684301487},
{"learn":[3.055810414],"iteration":991,"passed_time":0.7365799172,"remaining_time":0.005940160623},
{"learn":[3.055476518],"iteration":992,"passed_time":0.7370922866,"remaining_time":0.005196018133},
{"learn":[3.053331734],"iteration":993,"passed_time":0.7376447905,"remaining_time":0.004452584249},
{"learn":[3.050890374],"iteration":994,"passed_time":0.7381567822,"remaining_time":0.003709330564},
{"learn":[3.04972623],"iteration":995,"passed_time":0.7387178641,"remaining_time":0.00296673841},
{"learn":[3.047217327],"iteration":996,"passed_time":0.7392645772,"remaining_time":0.002224467133},
{"learn":[3.047155483],"iteration":997,"passed_time":0.7397244854,"remaining_time":0.001482413798},
{"learn":[3.04430671],"iteration":998,"passed_time":0.7402998705,"remaining_time":0.0007410409114},
{"learn":[3.042664195],"iteration":999,"passed_time":0.740820882,"remaining_time":0}
]}